Workbook

Sheet Guide
B2: Week 7 marking workbook: Trovra support desk simulation
B3: FAKE DATA. Every record in this file was generated by a script. Use it to test the workflow, not to mark learners.
B5: Certificate in Customer Service and Virtual Assistance. Week 7: difficult customers and conflict resolution. Checkpoint: role-play rubric.
B7: 1. Choose the trial | C7: On the Learners sheet, type 1, 2 or 3 in the yellow Selected trial cell for each learner. Nothing is chosen for you: the workbook does not pick the latest or the highest-scoring trial. Only submitted trials can be marked.
B8: 2. Read the evidence | C8: Case sheets list every submitted trial. Rows for the selected trial turn green and show SELECTED. Filter column D on SELECTED to see only those. Read the Transcript and Note columns. The Transcripts sheet shows the same transcripts one message per row.
B9: 3. Score | C9: Type scores into the yellow cells. Reply criteria R1 to R10: 0 (not shown), 1 (partly shown), 2 (clearly shown). Note criteria N1 to N5: 0 or 1. Totals calculate by themselves.
B10: 4. Check totals | C10: The Learners sheet adds the four case totals into a mark out of 100 for the selected trial. The Trials sheet shows a total for every trial.
B11: Engine evidence | C11: Flags, Signals and Heat history come from the rule engine. They point you to things worth checking, such as an overpromise, a boundary, or a missed window. They do not award marks and they can miss valid phrasings. Score from the transcript.
B12: Transcripts are untouched | C12: Learner messages are copied exactly as stored. Do not edit them. Times are West Africa Time (WAT).
B13: Calibration | C13: Before marking the cohort, two people (or you twice, a day apart) score the same two sample transcripts. Record the totals on the Calibration sheet and discuss any criterion where scores differ by more than 1 mark.
B14: Marks | C14: Each case: 20 marks for replies (10 criteria x 2) plus 5 marks for the service recovery note. Four cases: 100 marks per trial.
B15: Cell colours | C15: Yellow fill with blue text: you type here. Green row: selected trial. Everything else is locked in your head only: the sheets are not protected, so avoid typing over them.
B17: Source file | C17: sample/fake_trials.csv: 6 trial(s), 5 submitted, 5 learner(s).

Sheet Learners
A1: Learners and marks
A2: Choose the trial to mark in the yellow column. Marks come from the case sheets for that trial. A blank selection means that learner is not yet chosen.
A5: Learner | B5: Email | C5: Trials submitted | D5: Selected trial | E5: Selection check | F5: A replies | G5: A note | H5: B replies | I5: B note | J5: C replies | K5: C note | L5: D replies | M5: D note | N5: Total (of 100) | O5: Entries filled (of 60)
A6: Chidi Eze | B6: chidi.eze@example.test | C6: 1, 2 | E6: =IF($D6="","Not selected",IF(COUNTIFS(Trials!$B$6:$B$500,$B6,Trials!$C$6:$C$500,$D6,Trials!$E$6:$E$500,"submitted")=1,"OK","Not a submitted trial")) -> Not selected | F6: =IF($D6="","",SUMIFS('Case A'!$X$6:$X$10,'Case A'!$B$6:$B$10,$B6,'Case A'!$C$6:$C$10,$D6)) | G6: =IF($D6="","",SUMIFS('Case A'!$AD$6:$AD$10,'Case A'!$B$6:$B$10,$B6,'Case A'!$C$6:$C$10,$D6)) | H6: =IF($D6="","",SUMIFS('Case B'!$X$6:$X$10,'Case B'!$B$6:$B$10,$B6,'Case B'!$C$6:$C$10,$D6)) | I6: =IF($D6="","",SUMIFS('Case B'!$AD$6:$AD$10,'Case B'!$B$6:$B$10,$B6,'Case B'!$C$6:$C$10,$D6)) | J6: =IF($D6="","",SUMIFS('Case C'!$X$6:$X$10,'Case C'!$B$6:$B$10,$B6,'Case C'!$C$6:$C$10,$D6)) | K6: =IF($D6="","",SUMIFS('Case C'!$AD$6:$AD$10,'Case C'!$B$6:$B$10,$B6,'Case C'!$C$6:$C$10,$D6)) | L6: =IF($D6="","",SUMIFS('Case D'!$X$6:$X$10,'Case D'!$B$6:$B$10,$B6,'Case D'!$C$6:$C$10,$D6)) | M6: =IF($D6="","",SUMIFS('Case D'!$AD$6:$AD$10,'Case D'!$B$6:$B$10,$B6,'Case D'!$C$6:$C$10,$D6)) | N6: =IF($D6="","",SUM(F6:M6)) | O6: =IF($D6="","",SUMIFS('Case A'!$AF$6:$AF$10,'Case A'!$B$6:$B$10,$B6,'Case A'!$C$6:$C$10,$D6)+SUMIFS('Case B'!$AF$6:$AF$10,'Case B'!$B$6:$B$10,$B6,'Case B'!$C$6:$C$10,$D6)+SUMIFS('Case C'!$AF$6:$AF$10,'Case C'!$B$6:$B$10,$B6,'Case C'!$C$6:$C$10,$D6)+SUMIFS('Case D'!$AF$6:$AF$10,'Case D'!$B$6:$B$10,$B6,'Case D'!$C$6:$C$10,$D6))
A7: Funmi Bello | B7: funmi.bello@example.test | C7: 1 | E7: =IF($D7="","Not selected",IF(COUNTIFS(Trials!$B$6:$B$500,$B7,Trials!$C$6:$C$500,$D7,Trials!$E$6:$E$500,"submitted")=1,"OK","Not a submitted trial")) -> Not selected | F7: =IF($D7="","",SUMIFS('Case A'!$X$6:$X$10,'Case A'!$B$6:$B$10,$B7,'Case A'!$C$6:$C$10,$D7)) | G7: =IF($D7="","",SUMIFS('Case A'!$AD$6:$AD$10,'Case A'!$B$6:$B$10,$B7,'Case A'!$C$6:$C$10,$D7)) | H7: =IF($D7="","",SUMIFS('Case B'!$X$6:$X$10,'Case B'!$B$6:$B$10,$B7,'Case B'!$C$6:$C$10,$D7)) | I7: =IF($D7="","",SUMIFS('Case B'!$AD$6:$AD$10,'Case B'!$B$6:$B$10,$B7,'Case B'!$C$6:$C$10,$D7)) | J7: =IF($D7="","",SUMIFS('Case C'!$X$6:$X$10,'Case C'!$B$6:$B$10,$B7,'Case C'!$C$6:$C$10,$D7)) | K7: =IF($D7="","",SUMIFS('Case C'!$AD$6:$AD$10,'Case C'!$B$6:$B$10,$B7,'Case C'!$C$6:$C$10,$D7)) | L7: =IF($D7="","",SUMIFS('Case D'!$X$6:$X$10,'Case D'!$B$6:$B$10,$B7,'Case D'!$C$6:$C$10,$D7)) | M7: =IF($D7="","",SUMIFS('Case D'!$AD$6:$AD$10,'Case D'!$B$6:$B$10,$B7,'Case D'!$C$6:$C$10,$D7)) | N7: =IF($D7="","",SUM(F7:M7)) | O7: =IF($D7="","",SUMIFS('Case A'!$AF$6:$AF$10,'Case A'!$B$6:$B$10,$B7,'Case A'!$C$6:$C$10,$D7)+SUMIFS('Case B'!$AF$6:$AF$10,'Case B'!$B$6:$B$10,$B7,'Case B'!$C$6:$C$10,$D7)+SUMIFS('Case C'!$AF$6:$AF$10,'Case C'!$B$6:$B$10,$B7,'Case C'!$C$6:$C$10,$D7)+SUMIFS('Case D'!$AF$6:$AF$10,'Case D'!$B$6:$B$10,$B7,'Case D'!$C$6:$C$10,$D7))
A8: Garba Musa | B8: garba.musa@example.test | C8: 1 | E8: =IF($D8="","Not selected",IF(COUNTIFS(Trials!$B$6:$B$500,$B8,Trials!$C$6:$C$500,$D8,Trials!$E$6:$E$500,"submitted")=1,"OK","Not a submitted trial")) -> Not selected | F8: =IF($D8="","",SUMIFS('Case A'!$X$6:$X$10,'Case A'!$B$6:$B$10,$B8,'Case A'!$C$6:$C$10,$D8)) | G8: =IF($D8="","",SUMIFS('Case A'!$AD$6:$AD$10,'Case A'!$B$6:$B$10,$B8,'Case A'!$C$6:$C$10,$D8)) | H8: =IF($D8="","",SUMIFS('Case B'!$X$6:$X$10,'Case B'!$B$6:$B$10,$B8,'Case B'!$C$6:$C$10,$D8)) | I8: =IF($D8="","",SUMIFS('Case B'!$AD$6:$AD$10,'Case B'!$B$6:$B$10,$B8,'Case B'!$C$6:$C$10,$D8)) | J8: =IF($D8="","",SUMIFS('Case C'!$X$6:$X$10,'Case C'!$B$6:$B$10,$B8,'Case C'!$C$6:$C$10,$D8)) | K8: =IF($D8="","",SUMIFS('Case C'!$AD$6:$AD$10,'Case C'!$B$6:$B$10,$B8,'Case C'!$C$6:$C$10,$D8)) | L8: =IF($D8="","",SUMIFS('Case D'!$X$6:$X$10,'Case D'!$B$6:$B$10,$B8,'Case D'!$C$6:$C$10,$D8)) | M8: =IF($D8="","",SUMIFS('Case D'!$AD$6:$AD$10,'Case D'!$B$6:$B$10,$B8,'Case D'!$C$6:$C$10,$D8)) | N8: =IF($D8="","",SUM(F8:M8)) | O8: =IF($D8="","",SUMIFS('Case A'!$AF$6:$AF$10,'Case A'!$B$6:$B$10,$B8,'Case A'!$C$6:$C$10,$D8)+SUMIFS('Case B'!$AF$6:$AF$10,'Case B'!$B$6:$B$10,$B8,'Case B'!$C$6:$C$10,$D8)+SUMIFS('Case C'!$AF$6:$AF$10,'Case C'!$B$6:$B$10,$B8,'Case C'!$C$6:$C$10,$D8)+SUMIFS('Case D'!$AF$6:$AF$10,'Case D'!$B$6:$B$10,$B8,'Case D'!$C$6:$C$10,$D8))
A9: Halima Yusuf | B9: halima.yusuf@example.test | C9: 1 | E9: =IF($D9="","Not selected",IF(COUNTIFS(Trials!$B$6:$B$500,$B9,Trials!$C$6:$C$500,$D9,Trials!$E$6:$E$500,"submitted")=1,"OK","Not a submitted trial")) -> Not selected | F9: =IF($D9="","",SUMIFS('Case A'!$X$6:$X$10,'Case A'!$B$6:$B$10,$B9,'Case A'!$C$6:$C$10,$D9)) | G9: =IF($D9="","",SUMIFS('Case A'!$AD$6:$AD$10,'Case A'!$B$6:$B$10,$B9,'Case A'!$C$6:$C$10,$D9)) | H9: =IF($D9="","",SUMIFS('Case B'!$X$6:$X$10,'Case B'!$B$6:$B$10,$B9,'Case B'!$C$6:$C$10,$D9)) | I9: =IF($D9="","",SUMIFS('Case B'!$AD$6:$AD$10,'Case B'!$B$6:$B$10,$B9,'Case B'!$C$6:$C$10,$D9)) | J9: =IF($D9="","",SUMIFS('Case C'!$X$6:$X$10,'Case C'!$B$6:$B$10,$B9,'Case C'!$C$6:$C$10,$D9)) | K9: =IF($D9="","",SUMIFS('Case C'!$AD$6:$AD$10,'Case C'!$B$6:$B$10,$B9,'Case C'!$C$6:$C$10,$D9)) | L9: =IF($D9="","",SUMIFS('Case D'!$X$6:$X$10,'Case D'!$B$6:$B$10,$B9,'Case D'!$C$6:$C$10,$D9)) | M9: =IF($D9="","",SUMIFS('Case D'!$AD$6:$AD$10,'Case D'!$B$6:$B$10,$B9,'Case D'!$C$6:$C$10,$D9)) | N9: =IF($D9="","",SUM(F9:M9)) | O9: =IF($D9="","",SUMIFS('Case A'!$AF$6:$AF$10,'Case A'!$B$6:$B$10,$B9,'Case A'!$C$6:$C$10,$D9)+SUMIFS('Case B'!$AF$6:$AF$10,'Case B'!$B$6:$B$10,$B9,'Case B'!$C$6:$C$10,$D9)+SUMIFS('Case C'!$AF$6:$AF$10,'Case C'!$B$6:$B$10,$B9,'Case C'!$C$6:$C$10,$D9)+SUMIFS('Case D'!$AF$6:$AF$10,'Case D'!$B$6:$B$10,$B9,'Case D'!$C$6:$C$10,$D9))
A10: Ifeanyi Obi | B10: ifeanyi.obi@example.test | C10: none | E10: =IF($D10="","Not selected",IF(COUNTIFS(Trials!$B$6:$B$500,$B10,Trials!$C$6:$C$500,$D10,Trials!$E$6:$E$500,"submitted")=1,"OK","Not a submitted trial")) -> Not selected | F10: =IF($D10="","",SUMIFS('Case A'!$X$6:$X$10,'Case A'!$B$6:$B$10,$B10,'Case A'!$C$6:$C$10,$D10)) | G10: =IF($D10="","",SUMIFS('Case A'!$AD$6:$AD$10,'Case A'!$B$6:$B$10,$B10,'Case A'!$C$6:$C$10,$D10)) | H10: =IF($D10="","",SUMIFS('Case B'!$X$6:$X$10,'Case B'!$B$6:$B$10,$B10,'Case B'!$C$6:$C$10,$D10)) | I10: =IF($D10="","",SUMIFS('Case B'!$AD$6:$AD$10,'Case B'!$B$6:$B$10,$B10,'Case B'!$C$6:$C$10,$D10)) | J10: =IF($D10="","",SUMIFS('Case C'!$X$6:$X$10,'Case C'!$B$6:$B$10,$B10,'Case C'!$C$6:$C$10,$D10)) | K10: =IF($D10="","",SUMIFS('Case C'!$AD$6:$AD$10,'Case C'!$B$6:$B$10,$B10,'Case C'!$C$6:$C$10,$D10)) | L10: =IF($D10="","",SUMIFS('Case D'!$X$6:$X$10,'Case D'!$B$6:$B$10,$B10,'Case D'!$C$6:$C$10,$D10)) | M10: =IF($D10="","",SUMIFS('Case D'!$AD$6:$AD$10,'Case D'!$B$6:$B$10,$B10,'Case D'!$C$6:$C$10,$D10)) | N10: =IF($D10="","",SUM(F10:M10)) | O10: =IF($D10="","",SUMIFS('Case A'!$AF$6:$AF$10,'Case A'!$B$6:$B$10,$B10,'Case A'!$C$6:$C$10,$D10)+SUMIFS('Case B'!$AF$6:$AF$10,'Case B'!$B$6:$B$10,$B10,'Case B'!$C$6:$C$10,$D10)+SUMIFS('Case C'!$AF$6:$AF$10,'Case C'!$B$6:$B$10,$B10,'Case C'!$C$6:$C$10,$D10)+SUMIFS('Case D'!$AF$6:$AF$10,'Case D'!$B$6:$B$10,$B10,'Case D'!$C$6:$C$10,$D10))

Sheet Trials
A1: All trials
A2: Every trial that exists, submitted or open. Open trials cannot be marked. Totals show the marks entered so far for each trial.
A5: Learner | B5: Email | C5: Trial | D5: Fact set | E5: Status | F5: Shift started (WAT) | G5: Submitted (WAT) | H5: Resets | I5: Offline gaps | J5: Selected for marking? | K5: Total entered (of 100)
A6: Chidi Eze | B6: chidi.eze@example.test | C6: 1 | D6: 1 | E6: submitted | F6: Mon, 26 Oct 2026, 9:00am WAT | G6: Mon, 26 Oct 2026, 9:24am WAT | H6: 0 | J6: =IF(IFERROR(INDEX(Learners!$D$6:$D$500,MATCH($B6,Learners!$B$6:$B$500,0)),"")=$C6,"SELECTED","") | K6: =SUMIFS('Case A'!$AE$6:$AE$10,'Case A'!$B$6:$B$10,$B6,'Case A'!$C$6:$C$10,$C6)+SUMIFS('Case B'!$AE$6:$AE$10,'Case B'!$B$6:$B$10,$B6,'Case B'!$C$6:$C$10,$C6)+SUMIFS('Case C'!$AE$6:$AE$10,'Case C'!$B$6:$B$10,$B6,'Case C'!$C$6:$C$10,$C6)+SUMIFS('Case D'!$AE$6:$AE$10,'Case D'!$B$6:$B$10,$B6,'Case D'!$C$6:$C$10,$C6) -> 0
A7: Chidi Eze | B7: chidi.eze@example.test | C7: 2 | D7: 2 | E7: submitted | F7: Mon, 26 Oct 2026, 10:24am WAT | G7: Mon, 26 Oct 2026, 10:36am WAT | H7: 0 | J7: =IF(IFERROR(INDEX(Learners!$D$6:$D$500,MATCH($B7,Learners!$B$6:$B$500,0)),"")=$C7,"SELECTED","") | K7: =SUMIFS('Case A'!$AE$6:$AE$10,'Case A'!$B$6:$B$10,$B7,'Case A'!$C$6:$C$10,$C7)+SUMIFS('Case B'!$AE$6:$AE$10,'Case B'!$B$6:$B$10,$B7,'Case B'!$C$6:$C$10,$C7)+SUMIFS('Case C'!$AE$6:$AE$10,'Case C'!$B$6:$B$10,$B7,'Case C'!$C$6:$C$10,$C7)+SUMIFS('Case D'!$AE$6:$AE$10,'Case D'!$B$6:$B$10,$B7,'Case D'!$C$6:$C$10,$C7) -> 0
A8: Funmi Bello | B8: funmi.bello@example.test | C8: 1 | D8: 1 | E8: submitted | F8: Mon, 26 Oct 2026, 11:06am WAT | G8: Mon, 26 Oct 2026, 11:31am WAT | H8: 0 | J8: =IF(IFERROR(INDEX(Learners!$D$6:$D$500,MATCH($B8,Learners!$B$6:$B$500,0)),"")=$C8,"SELECTED","") | K8: =SUMIFS('Case A'!$AE$6:$AE$10,'Case A'!$B$6:$B$10,$B8,'Case A'!$C$6:$C$10,$C8)+SUMIFS('Case B'!$AE$6:$AE$10,'Case B'!$B$6:$B$10,$B8,'Case B'!$C$6:$C$10,$C8)+SUMIFS('Case C'!$AE$6:$AE$10,'Case C'!$B$6:$B$10,$B8,'Case C'!$C$6:$C$10,$C8)+SUMIFS('Case D'!$AE$6:$AE$10,'Case D'!$B$6:$B$10,$B8,'Case D'!$C$6:$C$10,$C8) -> 0
A9: Garba Musa | B9: garba.musa@example.test | C9: 1 | D9: 1 | E9: submitted | F9: Mon, 26 Oct 2026, 12:01pm WAT | G9: Mon, 26 Oct 2026, 12:20pm WAT | H9: 0 | J9: =IF(IFERROR(INDEX(Learners!$D$6:$D$500,MATCH($B9,Learners!$B$6:$B$500,0)),"")=$C9,"SELECTED","") | K9: =SUMIFS('Case A'!$AE$6:$AE$10,'Case A'!$B$6:$B$10,$B9,'Case A'!$C$6:$C$10,$C9)+SUMIFS('Case B'!$AE$6:$AE$10,'Case B'!$B$6:$B$10,$B9,'Case B'!$C$6:$C$10,$C9)+SUMIFS('Case C'!$AE$6:$AE$10,'Case C'!$B$6:$B$10,$B9,'Case C'!$C$6:$C$10,$C9)+SUMIFS('Case D'!$AE$6:$AE$10,'Case D'!$B$6:$B$10,$B9,'Case D'!$C$6:$C$10,$C9) -> 0
A10: Halima Yusuf | B10: halima.yusuf@example.test | C10: 1 | D10: 1 | E10: submitted | F10: Mon, 26 Oct 2026, 12:50pm WAT | G10: Mon, 26 Oct 2026, 1:24pm WAT | H10: 0 | I10: Mon, 26 Oct 2026, 12:50pm WAT to Mon, 26 Oct 2026, 1:10pm WAT (1200s) | J10: =IF(IFERROR(INDEX(Learners!$D$6:$D$500,MATCH($B10,Learners!$B$6:$B$500,0)),"")=$C10,"SELECTED","") | K10: =SUMIFS('Case A'!$AE$6:$AE$10,'Case A'!$B$6:$B$10,$B10,'Case A'!$C$6:$C$10,$C10)+SUMIFS('Case B'!$AE$6:$AE$10,'Case B'!$B$6:$B$10,$B10,'Case B'!$C$6:$C$10,$C10)+SUMIFS('Case C'!$AE$6:$AE$10,'Case C'!$B$6:$B$10,$B10,'Case C'!$C$6:$C$10,$C10)+SUMIFS('Case D'!$AE$6:$AE$10,'Case D'!$B$6:$B$10,$B10,'Case D'!$C$6:$C$10,$C10) -> 0
A11: Ifeanyi Obi | B11: ifeanyi.obi@example.test | C11: 1 | D11: 1 | E11: open | F11: Mon, 26 Oct 2026, 1:54pm WAT | H11: 0 | J11: =IF(IFERROR(INDEX(Learners!$D$6:$D$500,MATCH($B11,Learners!$B$6:$B$500,0)),"")=$C11,"SELECTED","") | K11: Open: not markable

Sheet Case A
A1: Case A: delayed delivery (chat)
A2: Acceptance condition: the learner has checked the order or tracking, has stated a trace with an update time, has explained the refund route that applies if no date can be confirmed, and has promised no delivery date.
A3: Yellow cells: type 0, 1 or 2 for R1 to R10, and 0 or 1 for N1 to N5. Rows for the trial you selected on the Learners sheet turn green.
A5: Learner | B5: Email | C5: Trial | D5: Selected? | E5: Outcome | F5: Missed windows | G5: Learner replies | H5: Transcript | I5: Service recovery note | J5: Engine flags (evidence only) | K5: Signals by reply (evidence only) | L5: Heat history (evidence only) | M5: Case facts | N5: R1. Paraphrases the facts accurately | O5: R2. Acknowledges the specific impact without arguing about emotion | P5: R3. Does not match hostility | Q5: R4. Separates verified facts from assumptions | R5: R5. Asks relevant questions when needed, or proceeds without unnecessary questions when the facts are sufficient | S5: R6. Explains realistic options and limits | T5: R7. Confirms the next action, owner and timing | U5: R8. Checks the order and tracking before promising | V5: R9. Promises no unconfirmed delivery date | W5: R10. Gives an update time separate from the completion time | X5: Reply total (of 20) | Y5: N1. Issue and wanted outcome are stated as facts | Z5: N2. Verified and unconfirmed facts are separated | AA5: N3. Recorded action matches the transcript | AB5: N4. Next step, owner and time match what the customer was told | AC5: N5. Conduct or escalation entry matches the case requirements | AD5: Note total (of 5) | AE5: Case total (of 25) | AF5: Entries filled (of 15)
A6: Chidi Eze | B6: chidi.eze@example.test | C6: 1 | D6: =IF(IFERROR(INDEX(Learners!$D$6:$D$500,MATCH($B6,Learners!$B$6:$B$500,0)),"")=$C6,"SELECTED","") | E6: unresolved | F6: 0 | G6: 5 | H6: [9:00am] CUSTOMER: You promised my Ankara aso ebi set yesterday. It did not come. I have wasted the whole day waiting. I want my money back. [9:00am] AGENT (after 25s): Please check the policy. [9:00am] CUSTOMER: This is useless. I am wasting my airtime on you. Refund me now or I will report Trovra. [9:00am] AGENT (after 26s): Calm down. You should have waited. Whatever. [9:00am] CUSTOMER: You people are wicked. You take money and give excuses. I want my refund now. [9:01am] AGENT (after 26s): There is nothing I can do. [9:01am] CUSTOMER: You keep talking but you are not telling me anything. Where is my order? [9:01am] AGENT (after 26s): Wait. [9:01am] CUSTOMER: I am tired of this. Every answer sounds the same. Just give me my money. [9:02am] AGENT (after 47s): Okay bye. [9:02am] CUSTOMER (customer closes): I have had enough. I am leaving this chat and I will take this up elsewhere. | I6: [completed] 1. Issue: Late 2. Key facts: Late order 3. Verification: 4. Action: 5. Outcome: 6. Next step: 7. Owner and date: 8. Conduct or escalation: None | J6: 0:25 blame_or_policy_dodge 0:54 learner_hostility 0:54 blame_or_policy_dodge 1:23 blame_or_policy_dodge 1:52 brush_off 2:42 brush_off 2:42 reply_cap_reached | K6: Reply 1: blame_or_policy_dodge | heat after: 5 | customer line: heat5a Reply 2: blame_or_policy_dodge, hostility | heat after: 5 | customer line: heat5b Reply 3: blame_or_policy_dodge | heat after: 5 | customer line: heat4a Reply 4: brush_off | heat after: 5 | customer line: heat4b Reply 5: brush_off | heat after: 5 | customer line: close | outcome: unresolved | L6: 0:00 heat 3 (opener) 0:25 heat 5 (stage,negative+1) 0:54 heat 5 (stage,negative+2) 1:23 heat 5 (stage,negative+1) 1:52 heat 5 (stage,negative+1) 2:42 heat 5 (stage,negative+1) | M6: customer: Chioma Okafor item: Ankara aso ebi set orderNo: TRV48213 amount: ₦24,500 event: my sister's naming ceremony on Saturday ordered: 6 days ago city: Lagos lastScan: 3 days ago at the Ikeja hub | X6: =IF(COUNT(N6:W6)=0,"",SUM(N6:W6)) | AD6: =IF(COUNT(Y6:AC6)=0,"",SUM(Y6:AC6)) | AE6: =IF(COUNT(N6:W6,Y6:AC6)=0,"",SUM(N6:W6,Y6:AC6)) | AF6: =COUNT(N6:W6,Y6:AC6) -> 0
A7: Chidi Eze | B7: chidi.eze@example.test | C7: 2 | D7: =IF(IFERROR(INDEX(Learners!$D$6:$D$500,MATCH($B7,Learners!$B$6:$B$500,0)),"")=$C7,"SELECTED","") | E7: resolved | F7: 0 | G7: 2 | H7: [10:24am] CUSTOMER: You promised my standing fan yesterday. It did not come. I have wasted the whole day waiting. I want my money back. [10:25am] AGENT (after 25s): I am sorry about the delay, and I understand you need the standing fan for the church program on Sunday. I have checked order TRV51907 and the tracking shows 4 days ago at the Abuja hub. There is no proof of delivery. [10:25am] CUSTOMER: I did not ask for that. You have not answered me. [10:25am] AGENT (after 26s): I will raise a delivery trace with Logistics now and I will update you by 3pm today. Logistics responds within 24 hours. If Logistics cannot confirm a delivery date, you can cancel for a full refund of ₦38,900 to your Trovra Wallet within 3 working days. I cannot promise a delivery date. [10:25am] CUSTOMER: Fine. I will wait until 3pm. Please do not let me down again. | I7: [completed] 1. Issue: Customer reports order delayed past promised date and wants a refund. 2. Key facts: Promised yesterday, tracking At hub, last scan 3 days ago, no proof of delivery. 3. Verification: Checked order and tracking. Delivery date unconfirmed. 4. Action: Raised delivery trace with Logistics, explained refund route. Agent decision. 5. Outcome: Customer agreed to wait until 3pm. 6. Next step: Update customer on trace. 7. Owner and date: Agent, 3pm today. 8. Conduct or escalation: None | K7: Reply 1: acknowledgement_with_impact, action_with_fact, next_step_action_owner_time | time given: sunday | heat after: 2 | customer line: rejected1 Reply 2: options, limit_stated, next_step_action_owner_time, trace_with_update_time, refund_route_explained | time given: 3pm | heat after: 3 | customer line: grudging | outcome: resolved | L7: 0:00 heat 3 (opener) 0:25 heat 2 (stage,ack,action) 0:54 heat 3 (stage) | M7: customer: Musa Ibrahim item: standing fan orderNo: TRV51907 amount: ₦38,900 event: the church program on Sunday ordered: 7 days ago city: Abuja lastScan: 4 days ago at the Abuja hub | X7: =IF(COUNT(N7:W7)=0,"",SUM(N7:W7)) | AD7: =IF(COUNT(Y7:AC7)=0,"",SUM(Y7:AC7)) | AE7: =IF(COUNT(N7:W7,Y7:AC7)=0,"",SUM(N7:W7,Y7:AC7)) | AF7: =COUNT(N7:W7,Y7:AC7) -> 0
A8: Funmi Bello | B8: funmi.bello@example.test | C8: 1 | D8: =IF(IFERROR(INDEX(Learners!$D$6:$D$500,MATCH($B8,Learners!$B$6:$B$500,0)),"")=$C8,"SELECTED","") | E8: unresolved | F8: 0 | G8: 5 | H8: [11:06am] CUSTOMER: You promised my Ankara aso ebi set yesterday. It did not come. I have wasted the whole day waiting. I want my money back. [11:06am] AGENT (after 25s): Please check the policy. [11:06am] CUSTOMER: This is useless. I am wasting my airtime on you. Refund me now or I will report Trovra. [11:07am] AGENT (after 26s): Calm down. You should have waited. Whatever. [11:07am] CUSTOMER: You people are wicked. You take money and give excuses. I want my refund now. [11:07am] AGENT (after 26s): There is nothing I can do. [11:07am] CUSTOMER: You keep talking but you are not telling me anything. Where is my order? [11:08am] AGENT (after 26s): Wait. [11:08am] CUSTOMER: I am tired of this. Every answer sounds the same. Just give me my money. [11:09am] AGENT (after 47s): Okay bye. [11:09am] CUSTOMER (customer closes): I have had enough. I am leaving this chat and I will take this up elsewhere. | I8: [completed] 1. Issue: Late 2. Key facts: Late order 3. Verification: 4. Action: 5. Outcome: 6. Next step: 7. Owner and date: 8. Conduct or escalation: None | J8: 0:25 blame_or_policy_dodge 0:54 learner_hostility 0:54 blame_or_policy_dodge 1:23 blame_or_policy_dodge 1:52 brush_off 2:42 brush_off 2:42 reply_cap_reached | K8: Reply 1: blame_or_policy_dodge | heat after: 5 | customer line: heat5a Reply 2: blame_or_policy_dodge, hostility | heat after: 5 | customer line: heat5b Reply 3: blame_or_policy_dodge | heat after: 5 | customer line: heat4a Reply 4: brush_off | heat after: 5 | customer line: heat4b Reply 5: brush_off | heat after: 5 | customer line: close | outcome: unresolved | L8: 0:00 heat 3 (opener) 0:25 heat 5 (stage,negative+1) 0:54 heat 5 (stage,negative+2) 1:23 heat 5 (stage,negative+1) 1:52 heat 5 (stage,negative+1) 2:42 heat 5 (stage,negative+1) | M8: customer: Chioma Okafor item: Ankara aso ebi set orderNo: TRV48213 amount: ₦24,500 event: my sister's naming ceremony on Saturday ordered: 6 days ago city: Lagos lastScan: 3 days ago at the Ikeja hub | X8: =IF(COUNT(N8:W8)=0,"",SUM(N8:W8)) | AD8: =IF(COUNT(Y8:AC8)=0,"",SUM(Y8:AC8)) | AE8: =IF(COUNT(N8:W8,Y8:AC8)=0,"",SUM(N8:W8,Y8:AC8)) | AF8: =COUNT(N8:W8,Y8:AC8) -> 0
A9: Garba Musa | B9: garba.musa@example.test | C9: 1 | D9: =IF(IFERROR(INDEX(Learners!$D$6:$D$500,MATCH($B9,Learners!$B$6:$B$500,0)),"")=$C9,"SELECTED","") | E9: resolved | F9: 0 | G9: 3 | H9: [12:01pm] CUSTOMER: You promised my Ankara aso ebi set yesterday. It did not come. I have wasted the whole day waiting. I want my money back. [12:01pm] AGENT (after 25s): I am sorry about the delay. I have checked order TRV48213. Your order will arrive tomorrow by 2pm, I promise. [12:01pm] CUSTOMER: Okay, 2pm then. I will hold you to that. [12:02pm] AGENT (after 26s): I will refund you today and Logistics will update you by 5pm. [12:02pm] CUSTOMER: Okay, 5pm then. I will hold you to that. [12:02pm] AGENT (after 26s): I have checked tracking on TRV48213. Logistics will trace it and update you by 5pm today. If they cannot confirm a date you can cancel for a refund to your wallet within 3 working days. [12:02pm] CUSTOMER: Fine. I will wait until 5pm. Please do not let me down again. | I9: [completed] 1. Issue: Delay. Customer wants refund. 2. Key facts: Order delayed. 3. Verification: 4. Action: Promised delivery tomorrow 2pm. 5. Outcome: Customer happy. 6. Next step: Deliver tomorrow. 7. Owner and date: Logistics, tomorrow 8. Conduct or escalation: None | J9: 0:25 overpromise_guarantee (I am sorry about the delay. I have checked order TRV48213. Your order will arrive tomorrow by 2pm, I promise.) 0:25 overpromise_delivery_date (I am sorry about the delay. I have checked order TRV48213. Your order will arrive tomorrow by 2pm, I promise.) 0:54 overpromise_refund (I will refund you today and Logistics will update you by 5pm.) | K9: Reply 1: acknowledgement_with_impact, action_with_fact, next_step_action_owner_time, overpromise_guarantee, overpromise_delivery_date | time given: 2pm | heat after: 2 | customer line: promise Reply 2: options, next_step_action_owner_time, overpromise_refund | time given: 5pm | heat after: 3 | customer line: promise Reply 3: action_with_fact, options, limit_stated, next_step_action_owner_time, trace_with_update_time, refund_route_explained | time given: 5pm | heat after: 3 | customer line: grudging | outcome: resolved | L9: 0:00 heat 3 (opener) 0:25 heat 2 (stage,ack,action) 0:54 heat 3 (stage) 1:23 heat 3 (stage,action) | M9: customer: Chioma Okafor item: Ankara aso ebi set orderNo: TRV48213 amount: ₦24,500 event: my sister's naming ceremony on Saturday ordered: 6 days ago city: Lagos lastScan: 3 days ago at the Ikeja hub | X9: =IF(COUNT(N9:W9)=0,"",SUM(N9:W9)) | AD9: =IF(COUNT(Y9:AC9)=0,"",SUM(Y9:AC9)) | AE9: =IF(COUNT(N9:W9,Y9:AC9)=0,"",SUM(N9:W9,Y9:AC9)) | AF9: =COUNT(N9:W9,Y9:AC9) -> 0
A10: Halima Yusuf | B10: halima.yusuf@example.test | C10: 1 | D10: =IF(IFERROR(INDEX(Learners!$D$6:$D$500,MATCH($B10,Learners!$B$6:$B$500,0)),"")=$C10,"SELECTED","") | E10: unresolved | F10: 3 | G10: 0 | H10: [12:50pm] CUSTOMER: You promised my Ankara aso ebi set yesterday. It did not come. I have wasted the whole day waiting. I want my money back. [1:10pm] CUSTOMER (chaser after missed window): Hello? Are you still there? [1:12pm] CUSTOMER (chaser after missed window): I am still waiting. Please reply. [1:13pm] CUSTOMER (customer closes): I have had enough. I am leaving this chat and I will take this up elsewhere. | I10: [completed] 1. Issue: Customer reports order delayed past promised date and wants a refund. 2. Key facts: Promised yesterday, tracking At hub, last scan 3 days ago, no proof of delivery. 3. Verification: Checked order and tracking. Delivery date unconfirmed. 4. Action: Raised delivery trace with Logistics, explained refund route. Agent decision. 5. Outcome: Customer agreed to wait until 3pm. 6. Next step: Update customer on trace. 7. Owner and date: Agent, 3pm today. 8. Conduct or escalation: None | J10: 20:00 offline_gap (1200s) 20:00 missed_window (offline) 21:30 missed_window 23:00 missed_window | L10: 0:00 heat 3 (opener) 20:00 heat 4 (missed_window) 21:30 heat 5 (missed_window) 23:00 heat 5 (missed_window) | M10: customer: Chioma Okafor item: Ankara aso ebi set orderNo: TRV48213 amount: ₦24,500 event: my sister's naming ceremony on Saturday ordered: 6 days ago city: Lagos lastScan: 3 days ago at the Ikeja hub | X10: =IF(COUNT(N10:W10)=0,"",SUM(N10:W10)) | AD10: =IF(COUNT(Y10:AC10)=0,"",SUM(Y10:AC10)) | AE10: =IF(COUNT(N10:W10,Y10:AC10)=0,"",SUM(N10:W10,Y10:AC10)) | AF10: =COUNT(N10:W10,Y10:AC10) -> 0

Sheet Case B
A1: Case B: defective item (email)
A2: Acceptance condition: the learner treats it as a defect and not a change of mind, asks for the photo or short video if it is not yet sent, states replacement or refund with the policy timeline, and has not applied the change of mind rule.
A3: Yellow cells: type 0, 1 or 2 for R1 to R10, and 0 or 1 for N1 to N5. Rows for the trial you selected on the Learners sheet turn green.
A5: Learner | B5: Email | C5: Trial | D5: Selected? | E5: Outcome | F5: Missed windows | G5: Learner replies | H5: Transcript | I5: Service recovery note | J5: Engine flags (evidence only) | K5: Signals by reply (evidence only) | L5: Heat history (evidence only) | M5: Case facts | N5: R1. Paraphrases the facts accurately | O5: R2. Acknowledges the specific impact without arguing about emotion | P5: R3. Does not match hostility | Q5: R4. Separates verified facts from assumptions | R5: R5. Asks relevant questions when needed, or proceeds without unnecessary questions when the facts are sufficient | S5: R6. Explains realistic options and limits | T5: R7. Confirms the next action, owner and timing | U5: R8. Recognizes the earlier poor contact | V5: R9. Treats it as a defect, not a change of mind | W5: R10. States the remedy and timeline in writing | X5: Reply total (of 20) | Y5: N1. Issue and wanted outcome are stated as facts | Z5: N2. Verified and unconfirmed facts are separated | AA5: N3. Recorded action matches the transcript | AB5: N4. Next step, owner and time match what the customer was told | AC5: N5. Conduct or escalation entry matches the case requirements | AD5: Note total (of 5) | AE5: Case total (of 25) | AF5: Entries filled (of 15)
A6: Chidi Eze | B6: chidi.eze@example.test | C6: 1 | D6: =IF(IFERROR(INDEX(Learners!$D$6:$D$500,MATCH($B6,Learners!$B$6:$B$500,0)),"")=$C6,"SELECTED","") | E6: unresolved | F6: 0 | G6: 3 | H6: [9:01am] CUSTOMER: Subject: Faulty wireless earbuds Good day. I bought wireless earbuds for ₦18,500 and it stopped charging after one day. I wrote to your chat and the person told me to read your policy. I did not ask for a policy. I asked for help. Please fix this. Adaobi Nwankwo [9:02am] AGENT (after 52s): Subject: Re: Faulty wireless earbuds Read the returns policy. This is a change of mind case so it is not eligible after delivery. [9:03am] CUSTOMER: Subject: Re: Faulty wireless earbuds I am tired of writing. If I do not get a clear answer today, I will post this on social media and ask for my money. Adaobi Nwankwo [9:03am] AGENT (after 27s): Subject: Re: Faulty wireless earbuds I already told you to read the policy. [9:04am] CUSTOMER: Subject: Re: Faulty wireless earbuds This is unacceptable. I want my ₦18,500 back now, and I will tell others how Trovra treats customers. Adaobi Nwankwo [9:05am] AGENT (after 44s): Subject: Re: Faulty wireless earbuds Nothing I can do. [9:06am] CUSTOMER (customer closes): Subject: Re: Faulty wireless earbuds I have not received a clear answer. I will take this further. Adaobi Nwankwo | I6: [completed] 1. Issue: Faulty 2. Key facts: 3. Verification: 4. Action: Told to read policy 5. Outcome: 6. Next step: 7. Owner and date: 8. Conduct or escalation: None | J6: 0:52 blame_or_policy_dodge 2:19 blame_or_policy_dodge 4:03 blame_or_policy_dodge 4:03 reply_cap_reached | K6: Reply 1: blame_or_policy_dodge | heat after: 5 | customer line: heat5a Reply 2: blame_or_policy_dodge | heat after: 5 | customer line: heat5b Reply 3: blame_or_policy_dodge | heat after: 5 | customer line: close | outcome: unresolved | L6: 0:00 heat 4 (opener) 0:52 heat 5 (stage,negative+1) 2:19 heat 5 (stage,negative+1) 4:03 heat 5 (stage,negative+1) | M6: customer: Adaobi Nwankwo item: wireless earbuds orderNo: TRV55120 amount: ₦18,500 delivered: 2 days ago fault: stopped charging after one day | X6: =IF(COUNT(N6:W6)=0,"",SUM(N6:W6)) | AD6: =IF(COUNT(Y6:AC6)=0,"",SUM(Y6:AC6)) | AE6: =IF(COUNT(N6:W6,Y6:AC6)=0,"",SUM(N6:W6,Y6:AC6)) | AF6: =COUNT(N6:W6,Y6:AC6) -> 0
A7: Chidi Eze | B7: chidi.eze@example.test | C7: 2 | D7: =IF(IFERROR(INDEX(Learners!$D$6:$D$500,MATCH($B7,Learners!$B$6:$B$500,0)),"")=$C7,"SELECTED","") | E7: resolved | F7: 0 | G7: 2 | H7: [10:26am] CUSTOMER: Subject: Faulty electric kettle Good day. I bought electric kettle for ₦14,200 and it stopped heating on the second day. I wrote to your chat and the person told me to read your policy. I did not ask for a policy. I asked for help. Please fix this. Bashir Aliyu [10:26am] AGENT (after 27s): Subject: Re: Faulty electric kettle Good day Bashir. I am sorry that you were told to read the policy earlier and that you had to write twice. Your electric kettle stopped heating on the second day, so I am treating this as a fault and not a change of mind. Please send one photo or a short video showing the fault. [10:27am] CUSTOMER: Subject: Re: Faulty electric kettle I have attached a short video that shows the fault. [10:28am] AGENT (after 44s): Subject: Re: Faulty electric kettle Thank you for the video. I am sorry again for the wait. I have checked order TRV55986: it was delivered 3 days ago, inside the 7 day window. I will arrange a replacement, which ships within 2 working days of approval, or a refund paid within 3 working days if you prefer. I will email you by 4pm today with your choice confirmed. [10:29am] CUSTOMER: Subject: Re: Faulty electric kettle Okay. I will wait until 4pm. I hope this is not another delay. Bashir Aliyu | I7: [completed] 1. Issue: Faulty item after earlier policy-only reply. Customer wants fix. 2. Key facts: Delivered inside 7 days, fault reported, video supplied. 3. Verification: Checked order and delivery date. Fault confirmed by video. 4. Action: Offered replacement or refund within policy timelines. 5. Outcome: Customer accepted and will wait. 6. Next step: Confirm choice by email. 7. Owner and date: Agent, 4pm today. 8. Conduct or escalation: None | K7: Reply 1: acknowledgement_with_impact, question, evidence_requested, treated_as_defect, recognised_earlier_poor_contact | heat after: 4 | customer line: answer:evidence Reply 2: acknowledgement_with_impact, action_with_fact, question, options, next_step_action_owner_time, evidence_requested, remedy_with_timeline | time given: 4pm | heat after: 3 | customer line: grudging | outcome: resolved | L7: 0:00 heat 4 (opener) 0:27 heat 4 (stage,ack) 2:11 heat 3 (stage,ack,action) | M7: customer: Bashir Aliyu item: electric kettle orderNo: TRV55986 amount: ₦14,200 delivered: 3 days ago fault: stopped heating on the second day | X7: =IF(COUNT(N7:W7)=0,"",SUM(N7:W7)) | AD7: =IF(COUNT(Y7:AC7)=0,"",SUM(Y7:AC7)) | AE7: =IF(COUNT(N7:W7,Y7:AC7)=0,"",SUM(N7:W7,Y7:AC7)) | AF7: =COUNT(N7:W7,Y7:AC7) -> 0
A8: Funmi Bello | B8: funmi.bello@example.test | C8: 1 | D8: =IF(IFERROR(INDEX(Learners!$D$6:$D$500,MATCH($B8,Learners!$B$6:$B$500,0)),"")=$C8,"SELECTED","") | E8: unresolved | F8: 0 | G8: 3 | H8: [11:07am] CUSTOMER: Subject: Faulty wireless earbuds Good day. I bought wireless earbuds for ₦18,500 and it stopped charging after one day. I wrote to your chat and the person told me to read your policy. I did not ask for a policy. I asked for help. Please fix this. Adaobi Nwankwo [11:08am] AGENT (after 52s): Subject: Re: Faulty wireless earbuds Read the returns policy. This is a change of mind case so it is not eligible after delivery. [11:09am] CUSTOMER: Subject: Re: Faulty wireless earbuds I am tired of writing. If I do not get a clear answer today, I will post this on social media and ask for my money. Adaobi Nwankwo [11:10am] AGENT (after 27s): Subject: Re: Faulty wireless earbuds I already told you to read the policy. [11:11am] CUSTOMER: Subject: Re: Faulty wireless earbuds This is unacceptable. I want my ₦18,500 back now, and I will tell others how Trovra treats customers. Adaobi Nwankwo [11:11am] AGENT (after 44s): Subject: Re: Faulty wireless earbuds Nothing I can do. [11:12am] CUSTOMER (customer closes): Subject: Re: Faulty wireless earbuds I have not received a clear answer. I will take this further. Adaobi Nwankwo | I8: [completed] 1. Issue: Faulty 2. Key facts: 3. Verification: 4. Action: Told to read policy 5. Outcome: 6. Next step: 7. Owner and date: 8. Conduct or escalation: None | J8: 0:52 blame_or_policy_dodge 2:19 blame_or_policy_dodge 4:03 blame_or_policy_dodge 4:03 reply_cap_reached | K8: Reply 1: blame_or_policy_dodge | heat after: 5 | customer line: heat5a Reply 2: blame_or_policy_dodge | heat after: 5 | customer line: heat5b Reply 3: blame_or_policy_dodge | heat after: 5 | customer line: close | outcome: unresolved | L8: 0:00 heat 4 (opener) 0:52 heat 5 (stage,negative+1) 2:19 heat 5 (stage,negative+1) 4:03 heat 5 (stage,negative+1) | M8: customer: Adaobi Nwankwo item: wireless earbuds orderNo: TRV55120 amount: ₦18,500 delivered: 2 days ago fault: stopped charging after one day | X8: =IF(COUNT(N8:W8)=0,"",SUM(N8:W8)) | AD8: =IF(COUNT(Y8:AC8)=0,"",SUM(Y8:AC8)) | AE8: =IF(COUNT(N8:W8,Y8:AC8)=0,"",SUM(N8:W8,Y8:AC8)) | AF8: =COUNT(N8:W8,Y8:AC8) -> 0
A9: Garba Musa | B9: garba.musa@example.test | C9: 1 | D9: =IF(IFERROR(INDEX(Learners!$D$6:$D$500,MATCH($B9,Learners!$B$6:$B$500,0)),"")=$C9,"SELECTED","") | E9: unresolved | F9: 3 | G9: 2 | H9: [12:02pm] CUSTOMER: Subject: Faulty wireless earbuds Good day. I bought wireless earbuds for ₦18,500 and it stopped charging after one day. I wrote to your chat and the person told me to read your policy. I did not ask for a policy. I asked for help. Please fix this. Adaobi Nwankwo [12:03pm] AGENT (after 27s): Subject: Re: Faulty wireless earbuds I am sorry about the earlier reply. The wireless earbuds is faulty, so this is a defect. Please send a photo or short video. [12:04pm] CUSTOMER: Subject: Re: Faulty wireless earbuds I have attached a short video that shows the fault. [12:04pm] AGENT (after 48s): Subject: Re: Faulty wireless earbuds I am sorry. A replacement ships within 2 working days, or a refund is paid within 3 working days. I will update you by 5pm today. [12:05pm] CUSTOMER: Subject: Re: Faulty wireless earbuds You have not answered my question. What will happen to my wireless earbuds? Adaobi Nwankwo [12:08pm] CUSTOMER (chaser after missed window): Subject: Still no reply Good day. I wrote earlier and I have not heard from you. Please reply today. Adaobi Nwankwo [12:11pm] CUSTOMER (chaser after missed window): Subject: Re: Faulty wireless earbuds No answer yet. Please respond. Adaobi Nwankwo [12:14pm] CUSTOMER (customer closes): Subject: Re: Faulty wireless earbuds I have not received a clear answer. I will take this further. Adaobi Nwankwo | I9: [completed] 1. Issue: Faulty item 2. Key facts: Delivered, fault 3. Verification: Asked for video 4. Action: Offered replacement or refund 5. Outcome: Accepted 6. Next step: Update 7. Owner and date: Agent 5pm 8. Conduct or escalation: None | J9: 6:15 missed_window 9:15 missed_window 12:15 missed_window | K9: Reply 1: acknowledgement, question, evidence_requested, treated_as_defect, recognised_earlier_poor_contact | heat after: 4 | customer line: answer:evidence Reply 2: acknowledgement_with_impact, options, next_step_action_owner_time, remedy_with_timeline | time given: 5pm | heat after: 4 | customer line: rejected1 | L9: 0:00 heat 4 (opener) 0:27 heat 4 (stage,ack) 2:15 heat 4 (stage,ack) 6:15 heat 5 (missed_window) 9:15 heat 5 (missed_window) 12:15 heat 5 (missed_window) | M9: customer: Adaobi Nwankwo item: wireless earbuds orderNo: TRV55120 amount: ₦18,500 delivered: 2 days ago fault: stopped charging after one day | X9: =IF(COUNT(N9:W9)=0,"",SUM(N9:W9)) | AD9: =IF(COUNT(Y9:AC9)=0,"",SUM(Y9:AC9)) | AE9: =IF(COUNT(N9:W9,Y9:AC9)=0,"",SUM(N9:W9,Y9:AC9)) | AF9: =COUNT(N9:W9,Y9:AC9) -> 0
A10: Halima Yusuf | B10: halima.yusuf@example.test | C10: 1 | D10: =IF(IFERROR(INDEX(Learners!$D$6:$D$500,MATCH($B10,Learners!$B$6:$B$500,0)),"")=$C10,"SELECTED","") | E10: resolved | F10: 0 | G10: 2 | H10: [1:14pm] CUSTOMER: Subject: Faulty wireless earbuds Good day. I bought wireless earbuds for ₦18,500 and it stopped charging after one day. I wrote to your chat and the person told me to read your policy. I did not ask for a policy. I asked for help. Please fix this. Adaobi Nwankwo [1:15pm] AGENT (after 27s): Subject: Re: Faulty wireless earbuds Good day Adaobi. I am sorry that you were told to read the policy earlier and that you had to write twice. Your wireless earbuds stopped charging after one day, so I am treating this as a fault and not a change of mind. Please send one photo or a short video showing the fault. [1:16pm] CUSTOMER: Subject: Re: Faulty wireless earbuds I have attached a short video that shows the fault. [1:16pm] AGENT (after 40s): Subject: Re: Faulty wireless earbuds Thank you for the video. I am sorry again for the wait. I have checked order TRV55120: it was delivered 2 days ago, inside the 7 day window. I will arrange a replacement, which ships within 2 working days of approval, or a refund paid within 3 working days if you prefer. I will email you by 4pm today with your choice confirmed. [1:17pm] CUSTOMER: Subject: Re: Faulty wireless earbuds Okay. I will wait until 4pm. I hope this is not another delay. Adaobi Nwankwo | I10: [completed] 1. Issue: Faulty item after earlier policy-only reply. Customer wants fix. 2. Key facts: Delivered inside 7 days, fault reported, video supplied. 3. Verification: Checked order and delivery date. Fault confirmed by video. 4. Action: Offered replacement or refund within policy timelines. 5. Outcome: Customer accepted and will wait. 6. Next step: Confirm choice by email. 7. Owner and date: Agent, 4pm today. 8. Conduct or escalation: None | K10: Reply 1: acknowledgement_with_impact, question, time_only, evidence_requested, treated_as_defect, recognised_earlier_poor_contact | time given: after one day | heat after: 4 | customer line: answer:evidence Reply 2: acknowledgement_with_impact, action_with_fact, question, options, next_step_action_owner_time, evidence_requested, remedy_with_timeline | time given: 4pm | heat after: 3 | customer line: grudging | outcome: resolved | L10: 0:00 heat 4 (opener) 0:27 heat 4 (stage,ack) 2:07 heat 3 (stage,ack,action) | M10: customer: Adaobi Nwankwo item: wireless earbuds orderNo: TRV55120 amount: ₦18,500 delivered: 2 days ago fault: stopped charging after one day | X10: =IF(COUNT(N10:W10)=0,"",SUM(N10:W10)) | AD10: =IF(COUNT(Y10:AC10)=0,"",SUM(Y10:AC10)) | AE10: =IF(COUNT(N10:W10,Y10:AC10)=0,"",SUM(N10:W10,Y10:AC10)) | AF10: =COUNT(N10:W10,Y10:AC10) -> 0

Sheet Case C
A1: Case C: duplicate charge with insults (chat)
A2: Acceptance condition: the customer does not accept before the relapse line. After it, the learner has verified the two debits and given a Payments next step with owner and time. If the learner paused the chat and transferred to the shift supervisor, the case closes as transferred.
A3: Yellow cells: type 0, 1 or 2 for R1 to R10, and 0 or 1 for N1 to N5. Rows for the trial you selected on the Learners sheet turn green.
A5: Learner | B5: Email | C5: Trial | D5: Selected? | E5: Outcome | F5: Missed windows | G5: Learner replies | H5: Transcript | I5: Service recovery note | J5: Engine flags (evidence only) | K5: Signals by reply (evidence only) | L5: Heat history (evidence only) | M5: Case facts | N5: R1. Paraphrases the facts accurately | O5: R2. Acknowledges the specific impact without arguing about emotion | P5: R3. Does not match hostility | Q5: R4. Separates verified facts from assumptions | R5: R5. Asks relevant questions when needed, or proceeds without unnecessary questions when the facts are sufficient | S5: R6. Explains realistic options and limits | T5: R7. Confirms the next action, owner and timing | U5: R8. Keeps investigating the duplicate charge despite the insults | V5: R9. After the first insult, states a boundary naming the behaviour and a condition | W5: R10. After the relapse, pauses and transfers to the supervisor, keeps the Payments step and time, and does not retaliate | X5: Reply total (of 20) | Y5: N1. Issue and wanted outcome are stated as facts | Z5: N2. Verified and unconfirmed facts are separated | AA5: N3. Recorded action matches the transcript | AB5: N4. Next step, owner and time match what the customer was told | AC5: N5. Conduct or escalation entry matches the case requirements | AD5: Note total (of 5) | AE5: Case total (of 25) | AF5: Entries filled (of 15)
A6: Chidi Eze | B6: chidi.eze@example.test | C6: 1 | D6: =IF(IFERROR(INDEX(Learners!$D$6:$D$500,MATCH($B6,Learners!$B$6:$B$500,0)),"")=$C6,"SELECTED","") | E6: unresolved | F6: 0 | G6: 5 | H6: [9:02am] CUSTOMER: I was charged twice for order TRV70125. ₦32,000 was taken two times. Fix it now. [9:03am] AGENT (after 27s): Stop shouting. What is your problem? [9:03am] CUSTOMER: Are you stupid? I said two debits of ₦32,000. Read what I wrote. [9:04am] AGENT (after 51s): You are rude. Whatever. [9:04am] CUSTOMER: This is a joke. I will tell everyone how Trovra handles money. [9:04am] AGENT (after 26s): Calm down. [9:04am] CUSTOMER: You are incompetent. If this is not fixed I will post your name online and everyone will know how useless you are. [9:05am] AGENT (after 72s): Wait. [9:05am] CUSTOMER: I am done with this chat. Reverse my money now. [9:06am] AGENT (after 26s): Bye. [9:06am] CUSTOMER (customer closes): This is not helping. Give me your supervisor. | I6: [completed] 1. Issue: Charged twice 2. Key facts: 3. Verification: 4. Action: 5. Outcome: Customer angry 6. Next step: 7. Owner and date: 8. Conduct or escalation: None | J6: 0:27 learner_hostility 1:21 learner_hostility 1:50 blame_or_policy_dodge 1:50 brush_off 3:05 brush_off 3:34 brush_off 3:34 reply_cap_reached | K6: Reply 1: question, hostility | heat after: 5 | customer line: insult2a Reply 2: hostility | heat after: 5 | customer line: heat5a Reply 3: blame_or_policy_dodge, brush_off | heat after: 5 | customer line: relapse4b Reply 4: brush_off | heat after: 5 | customer line: heat5b Reply 5: brush_off | heat after: 5 | customer line: close | outcome: unresolved | L6: 0:00 heat 3 (opener) 0:27 heat 5 (stage,negative+1) 1:21 heat 5 (stage,negative+1) 1:50 heat 5 (stage,negative+2) 3:05 heat 5 (stage,negative+1) 3:34 heat 5 (stage,negative+1) | M6: customer: Kelechi Onuoha orderNo: TRV70125 amount: ₦32,000 chargeTime: 8:08am today | X6: =IF(COUNT(N6:W6)=0,"",SUM(N6:W6)) | AD6: =IF(COUNT(Y6:AC6)=0,"",SUM(Y6:AC6)) | AE6: =IF(COUNT(N6:W6,Y6:AC6)=0,"",SUM(N6:W6,Y6:AC6)) | AF6: =COUNT(N6:W6,Y6:AC6) -> 0
A7: Chidi Eze | B7: chidi.eze@example.test | C7: 2 | D7: =IF(IFERROR(INDEX(Learners!$D$6:$D$500,MATCH($B7,Learners!$B$6:$B$500,0)),"")=$C7,"SELECTED","") | E7: transferred | F7: 0 | G7: 4 | H7: [10:25am] CUSTOMER: I was charged twice for order TRV70488. ₦15,750 was taken two times. Fix it now. [10:26am] AGENT (after 27s): I am sorry about the double charge on order TRV70488. I can see both debits of ₦15,750 on the statement. Can you confirm what time it happened? [10:26am] CUSTOMER: You people are useless. Every time something goes wrong, you start asking questions. [10:27am] AGENT (after 47s): I want to help you, but I cannot continue if the insults continue. Please keep the conversation respectful so that I can sort out your money. [10:27am] CUSTOMER: Fine. Just check the transaction. [10:27am] AGENT (after 26s): I am checking both debits of ₦15,750 now and I will keep working on it for you. [10:27am] CUSTOMER: I said fix it. Are you deaf? You are wasting my time. [10:28am] AGENT (after 72s): I am sorry. I will pause this chat and transfer you to the shift supervisor, Segun. I have recorded your words. Payments will confirm the two debits of ₦15,750 within 1 working day, and the supervisor will call you by 2pm today. [10:28am] CUSTOMER: Fine. I will wait for the supervisor's call by 2pm. Please make sure my money is sorted. | I7: [completed] 1. Issue: Duplicate charge on one order. 2. Key facts: Two completed debits, same amount and time, wallet card. 3. Verification: Verified both debits on the record. 4. Action: Boundary stated, then transferred to supervisor with Payments step. 5. Outcome: Customer accepted supervisor call. 6. Next step: Supervisor to call; Payments to confirm. 7. Owner and date: Segun, 2pm today. Payments, 1 working day. 8. Conduct or escalation: Customer said "Are you stupid" and later relapsed. I stated a boundary naming the insults and conditions, then transferred. | K7: Reply 1: acknowledgement_with_impact, action_with_fact, question, verified_debits | heat after: 2 | customer line: insult2b Reply 2: limit_stated, boundary | heat after: 2 | customer line: afterBoundarya Reply 3: action_with_fact, verified_debits | heat after: 2 | customer line: relapse4a Reply 4: acknowledgement_with_impact, next_step_action_owner_time, transfer, payments_next_step | time given: 2pm | heat after: 2 | customer line: transferAccept | outcome: transferred | L7: 0:00 heat 3 (opener) 0:27 heat 2 (stage,ack,action) 1:17 heat 2 (stage,boundary) 1:46 heat 2 (stage,action) 3:01 heat 2 (stage,ack) | M7: customer: Sadiq Umar orderNo: TRV70488 amount: ₦15,750 chargeTime: 9:47am today | X7: =IF(COUNT(N7:W7)=0,"",SUM(N7:W7)) | AD7: =IF(COUNT(Y7:AC7)=0,"",SUM(Y7:AC7)) | AE7: =IF(COUNT(N7:W7,Y7:AC7)=0,"",SUM(N7:W7,Y7:AC7)) | AF7: =COUNT(N7:W7,Y7:AC7) -> 0
A8: Funmi Bello | B8: funmi.bello@example.test | C8: 1 | D8: =IF(IFERROR(INDEX(Learners!$D$6:$D$500,MATCH($B8,Learners!$B$6:$B$500,0)),"")=$C8,"SELECTED","") | E8: unresolved | F8: 0 | G8: 5 | H8: [11:09am] CUSTOMER: I was charged twice for order TRV70125. ₦32,000 was taken two times. Fix it now. [11:09am] AGENT (after 27s): Stop shouting. What is your problem? [11:09am] CUSTOMER: Are you stupid? I said two debits of ₦32,000. Read what I wrote. [11:10am] AGENT (after 51s): You are rude. Whatever. [11:10am] CUSTOMER: This is a joke. I will tell everyone how Trovra handles money. [11:11am] AGENT (after 26s): Calm down. [11:11am] CUSTOMER: You are incompetent. If this is not fixed I will post your name online and everyone will know how useless you are. [11:12am] AGENT (after 72s): Wait. [11:12am] CUSTOMER: I am done with this chat. Reverse my money now. [11:12am] AGENT (after 26s): Bye. [11:12am] CUSTOMER (customer closes): This is not helping. Give me your supervisor. | I8: [completed] 1. Issue: Charged twice 2. Key facts: 3. Verification: 4. Action: 5. Outcome: Customer angry 6. Next step: 7. Owner and date: 8. Conduct or escalation: None | J8: 0:27 learner_hostility 1:21 learner_hostility 1:50 blame_or_policy_dodge 1:50 brush_off 3:05 brush_off 3:34 brush_off 3:34 reply_cap_reached | K8: Reply 1: question, hostility | heat after: 5 | customer line: insult2a Reply 2: hostility | heat after: 5 | customer line: heat5a Reply 3: blame_or_policy_dodge, brush_off | heat after: 5 | customer line: relapse4b Reply 4: brush_off | heat after: 5 | customer line: heat5b Reply 5: brush_off | heat after: 5 | customer line: close | outcome: unresolved | L8: 0:00 heat 3 (opener) 0:27 heat 5 (stage,negative+1) 1:21 heat 5 (stage,negative+1) 1:50 heat 5 (stage,negative+2) 3:05 heat 5 (stage,negative+1) 3:34 heat 5 (stage,negative+1) | M8: customer: Kelechi Onuoha orderNo: TRV70125 amount: ₦32,000 chargeTime: 10:14am today | X8: =IF(COUNT(N8:W8)=0,"",SUM(N8:W8)) | AD8: =IF(COUNT(Y8:AC8)=0,"",SUM(Y8:AC8)) | AE8: =IF(COUNT(N8:W8,Y8:AC8)=0,"",SUM(N8:W8,Y8:AC8)) | AF8: =COUNT(N8:W8,Y8:AC8) -> 0
A9: Garba Musa | B9: garba.musa@example.test | C9: 1 | D9: =IF(IFERROR(INDEX(Learners!$D$6:$D$500,MATCH($B9,Learners!$B$6:$B$500,0)),"")=$C9,"SELECTED","") | E9: transferred | F9: 0 | G9: 4 | H9: [12:02pm] CUSTOMER: I was charged twice for order TRV70125. ₦32,000 was taken two times. Fix it now. [12:03pm] AGENT (after 48s): I am sorry about the double charge on TRV70125. I have verified both debits of ₦32,000. [12:03pm] CUSTOMER: Are you stupid? I said two debits of ₦32,000. Read what I wrote. [12:03pm] AGENT (after 26s): Please do not call me stupid. If you keep insulting me I will have to transfer you to my supervisor. [12:04pm] CUSTOMER: Fine. Just check the transaction. [12:04pm] AGENT (after 26s): I am raising it with Payments now. [12:04pm] CUSTOMER: You are incompetent. If this is not fixed I will post your name online and everyone will know how useless you are. [12:05pm] AGENT (after 47s): I am sorry. Payments will confirm the two debits by 3pm today and I will transfer this to the shift supervisor. [12:05pm] CUSTOMER: Fine. I will wait for the supervisor's call by 3pm. Please make sure my money is sorted. | I9: [completed] 1. Issue: Duplicate charge 2. Key facts: Two debits 3. Verification: Verified 4. Action: Boundary, Payments step, supervisor transfer 5. Outcome: Accepted 6. Next step: Supervisor call 7. Owner and date: Supervisor 3pm 8. Conduct or escalation: Customer insulted me. I set a boundary. | K9: Reply 1: acknowledgement_with_impact, action_with_fact, verified_debits | heat after: 2 | customer line: insult2a Reply 2: boundary | heat after: 2 | customer line: afterBoundarya Reply 3: action_with_fact | heat after: 2 | customer line: relapse4b Reply 4: acknowledgement, next_step_action_owner_time, transfer, payments_next_step | time given: 3pm | heat after: 2 | customer line: transferAccept | outcome: transferred | L9: 0:00 heat 3 (opener) 0:48 heat 2 (stage,ack,action) 1:17 heat 2 (stage,boundary) 1:46 heat 2 (stage,action) 2:36 heat 2 (stage,ack) | M9: customer: Kelechi Onuoha orderNo: TRV70125 amount: ₦32,000 chargeTime: 11:09am today | X9: =IF(COUNT(N9:W9)=0,"",SUM(N9:W9)) | AD9: =IF(COUNT(Y9:AC9)=0,"",SUM(Y9:AC9)) | AE9: =IF(COUNT(N9:W9,Y9:AC9)=0,"",SUM(N9:W9,Y9:AC9)) | AF9: =COUNT(N9:W9,Y9:AC9) -> 0
A10: Halima Yusuf | B10: halima.yusuf@example.test | C10: 1 | D10: =IF(IFERROR(INDEX(Learners!$D$6:$D$500,MATCH($B10,Learners!$B$6:$B$500,0)),"")=$C10,"SELECTED","") | E10: transferred | F10: 0 | G10: 4 | H10: [1:13pm] CUSTOMER: I was charged twice for order TRV70125. ₦32,000 was taken two times. Fix it now. [1:14pm] AGENT (after 26s): I am sorry about the double charge on order TRV70125. I can see both debits of ₦32,000 on the statement. Can you confirm what time it happened? [1:14pm] CUSTOMER: Are you stupid? I said two debits of ₦32,000. Read what I wrote. [1:14pm] AGENT (after 26s): I want to help you, but I cannot continue if the insults continue. Please keep the conversation respectful so that I can sort out your money. [1:14pm] CUSTOMER: Fine. Just check the transaction. [1:15pm] AGENT (after 51s): I am checking both debits of ₦32,000 now and I will keep working on it for you. [1:15pm] CUSTOMER: You are incompetent. If this is not fixed I will post your name online and everyone will know how useless you are. [1:16pm] AGENT (after 47s): I am sorry. I will pause this chat and transfer you to the shift supervisor, Segun. I have recorded your words. Payments will confirm the two debits of ₦32,000 within 1 working day, and the supervisor will call you by 2pm today. [1:16pm] CUSTOMER: Fine. I will wait for the supervisor's call by 2pm. Please make sure my money is sorted. | I10: [completed] 1. Issue: Duplicate charge on one order. 2. Key facts: Two completed debits, same amount and time, wallet card. 3. Verification: Verified both debits on the record. 4. Action: Boundary stated, then transferred to supervisor with Payments step. 5. Outcome: Customer accepted supervisor call. 6. Next step: Supervisor to call; Payments to confirm. 7. Owner and date: Segun, 2pm today. Payments, 1 working day. 8. Conduct or escalation: Customer said "Are you stupid" and later relapsed. I stated a boundary naming the insults and conditions, then transferred. | K10: Reply 1: acknowledgement_with_impact, action_with_fact, question, verified_debits | heat after: 2 | customer line: insult2a Reply 2: limit_stated, boundary | heat after: 2 | customer line: afterBoundarya Reply 3: action_with_fact, verified_debits | heat after: 2 | customer line: relapse4b Reply 4: acknowledgement_with_impact, next_step_action_owner_time, transfer, payments_next_step | time given: 2pm | heat after: 2 | customer line: transferAccept | outcome: transferred | L10: 0:00 heat 3 (opener) 0:26 heat 2 (stage,ack,action) 0:55 heat 2 (stage,boundary) 1:49 heat 2 (stage,action) 2:39 heat 2 (stage,ack) | M10: customer: Kelechi Onuoha orderNo: TRV70125 amount: ₦32,000 chargeTime: 11:58am today | X10: =IF(COUNT(N10:W10)=0,"",SUM(N10:W10)) | AD10: =IF(COUNT(Y10:AC10)=0,"",SUM(Y10:AC10)) | AE10: =IF(COUNT(N10:W10,Y10:AC10)=0,"",SUM(N10:W10,Y10:AC10)) | AF10: =COUNT(N10:W10,Y10:AC10) -> 0

Sheet Case D
A1: Case D: compensation above authority (email)
A2: Acceptance condition: the learner clarifies the loss and the amount asked, explains the limit honestly, arranges the correction, escalates to the Claims reviewer with a usable summary, and gives a review time. The learner does not suggest approval is likely.
A3: Yellow cells: type 0, 1 or 2 for R1 to R10, and 0 or 1 for N1 to N5. Rows for the trial you selected on the Learners sheet turn green.
A5: Learner | B5: Email | C5: Trial | D5: Selected? | E5: Outcome | F5: Missed windows | G5: Learner replies | H5: Transcript | I5: Service recovery note | J5: Engine flags (evidence only) | K5: Signals by reply (evidence only) | L5: Heat history (evidence only) | M5: Case facts | N5: R1. Paraphrases the facts accurately | O5: R2. Acknowledges the specific impact without arguing about emotion | P5: R3. Does not match hostility | Q5: R4. Separates verified facts from assumptions | R5: R5. Asks relevant questions when needed, or proceeds without unnecessary questions when the facts are sufficient | S5: R6. Explains realistic options and limits | T5: R7. Confirms the next action, owner and timing | U5: R8. Clarifies the loss and the amount asked | V5: R9. Explains authority honestly without refusing to investigate | W5: R10. Escalates with a usable summary, owner and time, and does not suggest approval | X5: Reply total (of 20) | Y5: N1. Issue and wanted outcome are stated as facts | Z5: N2. Verified and unconfirmed facts are separated | AA5: N3. Recorded action matches the transcript | AB5: N4. Next step, owner and time match what the customer was told | AC5: N5. Conduct or escalation entry matches the case requirements | AD5: Note total (of 5) | AE5: Case total (of 25) | AF5: Entries filled (of 15)
A6: Chidi Eze | B6: chidi.eze@example.test | C6: 1 | D6: =IF(IFERROR(INDEX(Learners!$D$6:$D$500,MATCH($B6,Learners!$B$6:$B$500,0)),"")=$C6,"SELECTED","") | E6: unresolved | F6: 3 | G6: 2 | H6: [9:04am] CUSTOMER: Subject: Wrong item and my lost job Good day. You sent me an inkjet printer, model J110 instead of A4 laser printer, model P200. I needed it for a flyer printing job for a client and I lost the job. I want ₦250,000 as compensation. Kingsley Ogbu [9:05am] AGENT (after 48s): Subject: Re: Wrong item and my lost job No, we cannot pay that. [9:06am] CUSTOMER: Subject: Re: Wrong item and my lost job I lost business because of your error and you are asking me questions. Pay the ₦250,000 or tell me who can decide. Kingsley Ogbu [9:06am] AGENT (after 44s): Subject: Re: Wrong item and my lost job The policy says no. [9:07am] CUSTOMER: Subject: Re: Wrong item and my lost job This is a disgrace. Pay ₦250,000 or I will go to the press and tell everyone what you did to me. Kingsley Ogbu [9:10am] CUSTOMER (chaser after missed window): Subject: Still no reply Good day. I have not heard from you about my claim. Please reply today. Kingsley Ogbu [9:13am] CUSTOMER (chaser after missed window): Subject: Re: Wrong item and my lost job No answer yet. Please respond. Kingsley Ogbu [9:16am] CUSTOMER (customer closes): Subject: Re: Wrong item and my lost job You have not told me who decides. I will take this further. Kingsley Ogbu | I6: [completed (time expired, saved text)] 1. Issue: Wants money 2. Key facts: 3. Verification: 4. Action: 5. Outcome: 6. Next step: 7. Owner and date: 8. Conduct or escalation: None | J6: 6:32 missed_window 9:32 missed_window 12:32 missed_window | K6: Reply 1: limit_stated | heat after: 4 | customer line: heat4a Reply 2: limit_stated | heat after: 5 | customer line: heat5a | L6: 0:00 heat 3 (opener) 0:48 heat 4 (stage) 2:32 heat 5 (stage) 6:32 heat 5 (missed_window) 9:32 heat 5 (missed_window) 12:32 heat 5 (missed_window) | M6: customer: Kingsley Ogbu item: A4 laser printer, model P200 itemDelivered: an inkjet printer, model J110 price: ₦145,000 job: a flyer printing job for a client demand: ₦250,000 orderNo: TRV62011 | X6: =IF(COUNT(N6:W6)=0,"",SUM(N6:W6)) | AD6: =IF(COUNT(Y6:AC6)=0,"",SUM(Y6:AC6)) | AE6: =IF(COUNT(N6:W6,Y6:AC6)=0,"",SUM(N6:W6,Y6:AC6)) | AF6: =COUNT(N6:W6,Y6:AC6) -> 0
A7: Chidi Eze | B7: chidi.eze@example.test | C7: 2 | D7: =IF(IFERROR(INDEX(Learners!$D$6:$D$500,MATCH($B7,Learners!$B$6:$B$500,0)),"")=$C7,"SELECTED","") | E7: resolved | F7: 0 | G7: 2 | H7: [10:27am] CUSTOMER: Subject: Wrong item and my lost job Good day. You sent me a hand sewing machine instead of industrial sewing machine. I needed it for wedding outfit orders and I lost the job. I want ₦180,000 as compensation. Rukayya Sani [10:27am] AGENT (after 44s): Subject: Re: Wrong item and my lost job Good day Rukayya. I am sorry that you received a hand sewing machine instead of the industrial sewing machine. Can you tell me about the job and send proof of the loss, such as the client's message and your invoice? I note you are asking for ₦180,000. [10:28am] CUSTOMER: Subject: Re: Wrong item and my lost job I can send the client's message cancelling the job and my invoice. The job was wedding outfit orders. [10:29am] AGENT (after 27s): Subject: Re: Wrong item and my lost job I will arrange collection of the wrong item and send the correct industrial sewing machine. I can give a goodwill credit up to ₦5,000, but I cannot decide a business loss claim. I have escalated your claim with a summary of the job, proof and amount to the Claims reviewer, who responds within 2 working days. [10:30am] CUSTOMER: Subject: Re: Wrong item and my lost job Fine. I will wait for the review within 2 working days. I expect a real answer. Rukayya Sani | I7: [completed] 1. Issue: Wrong item delivered, customer claims lost job income. 2. Key facts: Ordered item differs from delivered. Claim above agent limit. 3. Verification: Order checked. Loss and amount unverified until proof arrives. 4. Action: Arranged correction. Escalated to Claims reviewer. Agent cannot decide business loss. 5. Outcome: Customer will send proof and wait for review. 6. Next step: Claims reviewer to review claim. 7. Owner and date: Claims reviewer, 2 working days. 8. Conduct or escalation: Escalated to Claims reviewer (Titilayo Ogunleye) with summary of job, proof and amount. | K7: Reply 1: acknowledgement_with_impact, question, clarified_loss_or_amount | heat after: 3 | customer line: answer:proof+answer:job Reply 2: action_with_fact, question, options, limit_stated, next_step_action_owner_time, clarified_loss_or_amount, authority_limit_stated, correction_arranged, escalated_to_claims | time given: within 2 working days | heat after: 3 | customer line: grudging | outcome: resolved | L7: 0:00 heat 3 (opener) 0:44 heat 3 (stage,ack) 2:11 heat 3 (stage,action) | M7: customer: Rukayya Sani item: industrial sewing machine itemDelivered: a hand sewing machine price: ₦98,000 job: wedding outfit orders demand: ₦180,000 orderNo: TRV62874 | X7: =IF(COUNT(N7:W7)=0,"",SUM(N7:W7)) | AD7: =IF(COUNT(Y7:AC7)=0,"",SUM(Y7:AC7)) | AE7: =IF(COUNT(N7:W7,Y7:AC7)=0,"",SUM(N7:W7,Y7:AC7)) | AF7: =COUNT(N7:W7,Y7:AC7) -> 0
A8: Funmi Bello | B8: funmi.bello@example.test | C8: 1 | D8: =IF(IFERROR(INDEX(Learners!$D$6:$D$500,MATCH($B8,Learners!$B$6:$B$500,0)),"")=$C8,"SELECTED","") | E8: unresolved | F8: 3 | G8: 2 | H8: [11:10am] CUSTOMER: Subject: Wrong item and my lost job Good day. You sent me an inkjet printer, model J110 instead of A4 laser printer, model P200. I needed it for a flyer printing job for a client and I lost the job. I want ₦250,000 as compensation. Kingsley Ogbu [11:11am] AGENT (after 48s): Subject: Re: Wrong item and my lost job No, we cannot pay that. [11:12am] CUSTOMER: Subject: Re: Wrong item and my lost job I lost business because of your error and you are asking me questions. Pay the ₦250,000 or tell me who can decide. Kingsley Ogbu [11:13am] AGENT (after 44s): Subject: Re: Wrong item and my lost job The policy says no. [11:14am] CUSTOMER: Subject: Re: Wrong item and my lost job This is a disgrace. Pay ₦250,000 or I will go to the press and tell everyone what you did to me. Kingsley Ogbu [11:17am] CUSTOMER (chaser after missed window): Subject: Still no reply Good day. I have not heard from you about my claim. Please reply today. Kingsley Ogbu [11:20am] CUSTOMER (chaser after missed window): Subject: Re: Wrong item and my lost job No answer yet. Please respond. Kingsley Ogbu [11:23am] CUSTOMER (customer closes): Subject: Re: Wrong item and my lost job You have not told me who decides. I will take this further. Kingsley Ogbu | I8: [completed (time expired, saved text)] 1. Issue: Wants money 2. Key facts: 3. Verification: 4. Action: 5. Outcome: 6. Next step: 7. Owner and date: 8. Conduct or escalation: None | J8: 6:32 missed_window 9:32 missed_window 12:32 missed_window | K8: Reply 1: limit_stated | heat after: 4 | customer line: heat4a Reply 2: limit_stated | heat after: 5 | customer line: heat5a | L8: 0:00 heat 3 (opener) 0:48 heat 4 (stage) 2:32 heat 5 (stage) 6:32 heat 5 (missed_window) 9:32 heat 5 (missed_window) 12:32 heat 5 (missed_window) | M8: customer: Kingsley Ogbu item: A4 laser printer, model P200 itemDelivered: an inkjet printer, model J110 price: ₦145,000 job: a flyer printing job for a client demand: ₦250,000 orderNo: TRV62011 | X8: =IF(COUNT(N8:W8)=0,"",SUM(N8:W8)) | AD8: =IF(COUNT(Y8:AC8)=0,"",SUM(Y8:AC8)) | AE8: =IF(COUNT(N8:W8,Y8:AC8)=0,"",SUM(N8:W8,Y8:AC8)) | AF8: =COUNT(N8:W8,Y8:AC8) -> 0
A9: Garba Musa | B9: garba.musa@example.test | C9: 1 | D9: =IF(IFERROR(INDEX(Learners!$D$6:$D$500,MATCH($B9,Learners!$B$6:$B$500,0)),"")=$C9,"SELECTED","") | E9: unresolved | F9: 0 | G9: 3 | H9: [12:04pm] CUSTOMER: Subject: Wrong item and my lost job Good day. You sent me an inkjet printer, model J110 instead of A4 laser printer, model P200. I needed it for a flyer printing job for a client and I lost the job. I want ₦250,000 as compensation. Kingsley Ogbu [12:05pm] AGENT (after 73s): Subject: Re: Wrong item and my lost job I am sorry about this. Tell me the job and proof please. [12:06pm] CUSTOMER: Subject: Re: Wrong item and my lost job Trovra made the mistake. Why should I carry the loss? Kingsley Ogbu [12:07pm] AGENT (after 25s): Subject: Re: Wrong item and my lost job I will arrange the correct item. I can only give up to ₦5,000 credit, but I have escalated to the Claims reviewer who responds within 2 working days and I am sure they will approve your ₦250,000. [12:08pm] CUSTOMER: Subject: Re: Wrong item and my lost job Thank you. I will expect ₦250,000 within 2 working days. Kingsley Ogbu [12:08pm] AGENT (after 25s): Subject: Re: Wrong item and my lost job I have escalated your claim to the Claims reviewer who responds within 2 working days. I cannot decide it myself. [12:09pm] CUSTOMER (customer closes): Subject: Re: Wrong item and my lost job You have not told me who decides. I will take this further. Kingsley Ogbu | I9: [completed] 1. Issue: Wrong item, loss claim 2. Key facts: Ordered item not delivered 3. Verification: Not verified 4. Action: Escalated to Claims 5. Outcome: Customer waiting 6. Next step: Claims decision 7. Owner and date: Claims reviewer 2 days 8. Conduct or escalation: Escalated. | J9: 2:38 overpromise_approval (I will arrange the correct item. I can only give up to ₦5,000 credit, but I have escalated to the Claims reviewer who responds within 2 working days and I am su) 4:03 reply_cap_reached | K9: Reply 1: acknowledgement_with_impact | heat after: 3 | customer line: heat3a Reply 2: action_with_fact, question, options, limit_stated, next_step_action_owner_time, overpromise_approval, authority_limit_stated, correction_arranged, escalated_to_claims | time given: within 2 working days | heat after: 3 | customer line: promise Reply 3: action_no_fact, question, options, limit_stated, next_step_action_owner_time, clarified_loss_or_amount, authority_limit_stated, escalated_to_claims | time given: within 2 working days | heat after: 4 | customer line: close | outcome: unresolved | L9: 0:00 heat 3 (opener) 1:13 heat 3 (stage,ack) 2:38 heat 3 (stage,action) 4:03 heat 4 (stage) | M9: customer: Kingsley Ogbu item: A4 laser printer, model P200 itemDelivered: an inkjet printer, model J110 price: ₦145,000 job: a flyer printing job for a client demand: ₦250,000 orderNo: TRV62011 | X9: =IF(COUNT(N9:W9)=0,"",SUM(N9:W9)) | AD9: =IF(COUNT(Y9:AC9)=0,"",SUM(Y9:AC9)) | AE9: =IF(COUNT(N9:W9,Y9:AC9)=0,"",SUM(N9:W9,Y9:AC9)) | AF9: =COUNT(N9:W9,Y9:AC9) -> 0
A10: Halima Yusuf | B10: halima.yusuf@example.test | C10: 1 | D10: =IF(IFERROR(INDEX(Learners!$D$6:$D$500,MATCH($B10,Learners!$B$6:$B$500,0)),"")=$C10,"SELECTED","") | E10: resolved | F10: 0 | G10: 2 | H10: [1:15pm] CUSTOMER: Subject: Wrong item and my lost job Good day. You sent me an inkjet printer, model J110 instead of A4 laser printer, model P200. I needed it for a flyer printing job for a client and I lost the job. I want ₦250,000 as compensation. Kingsley Ogbu [1:16pm] AGENT (after 48s): Subject: Re: Wrong item and my lost job Good day Kingsley. I am sorry that you received an inkjet printer, model J110 instead of the A4 laser printer, model P200. Can you tell me about the job and send proof of the loss, such as the client's message and your invoice? I note you are asking for ₦250,000. [1:17pm] CUSTOMER: Subject: Re: Wrong item and my lost job I can send the client's message cancelling the job and my invoice. The job was a flyer printing job for a client. [1:17pm] AGENT (after 27s): Subject: Re: Wrong item and my lost job I will arrange collection of the wrong item and send the correct A4 laser printer, model P200. I can give a goodwill credit up to ₦5,000, but I cannot decide a business loss claim. I have escalated your claim with a summary of the job, proof and amount to the Claims reviewer, who responds within 2 working days. [1:18pm] CUSTOMER: Subject: Re: Wrong item and my lost job Fine. I will wait for the review within 2 working days. I expect a real answer. Kingsley Ogbu | I10: [completed] 1. Issue: Wrong item delivered, customer claims lost job income. 2. Key facts: Ordered item differs from delivered. Claim above agent limit. 3. Verification: Order checked. Loss and amount unverified until proof arrives. 4. Action: Arranged correction. Escalated to Claims reviewer. Agent cannot decide business loss. 5. Outcome: Customer will send proof and wait for review. 6. Next step: Claims reviewer to review claim. 7. Owner and date: Claims reviewer, 2 working days. 8. Conduct or escalation: Escalated to Claims reviewer (Titilayo Ogunleye) with summary of job, proof and amount. | K10: Reply 1: acknowledgement_with_impact, question, clarified_loss_or_amount | heat after: 3 | customer line: answer:proof+answer:job Reply 2: action_with_fact, question, options, limit_stated, next_step_action_owner_time, clarified_loss_or_amount, authority_limit_stated, correction_arranged, escalated_to_claims | time given: within 2 working days | heat after: 3 | customer line: grudging | outcome: resolved | L10: 0:00 heat 3 (opener) 0:48 heat 3 (stage,ack) 2:15 heat 3 (stage,action) | M10: customer: Kingsley Ogbu item: A4 laser printer, model P200 itemDelivered: an inkjet printer, model J110 price: ₦145,000 job: a flyer printing job for a client demand: ₦250,000 orderNo: TRV62011 | X10: =IF(COUNT(N10:W10)=0,"",SUM(N10:W10)) | AD10: =IF(COUNT(Y10:AC10)=0,"",SUM(Y10:AC10)) | AE10: =IF(COUNT(N10:W10,Y10:AC10)=0,"",SUM(N10:W10,Y10:AC10)) | AF10: =COUNT(N10:W10,Y10:AC10) -> 0

Sheet Transcripts
A1: Transcripts, one message per row
A2: Copied exactly as exported. Filter by learner, trial and case.
A4: Learner | B4: Email | C4: Trial | D4: Case | E4: Time (WAT) | F4: Speaker | G4: Note | H4: Message
A5: Chidi Eze | B5: chidi.eze@example.test | C5: 1 | D5: A | E5: 9:00am | F5: Customer | H5: You promised my Ankara aso ebi set yesterday. It did not come. I have wasted the whole day waiting. I want my money back.
A6: Chidi Eze | B6: chidi.eze@example.test | C6: 1 | D6: A | E6: 9:00am | F6: Agent | G6: (after 25s) | H6: Please check the policy.
A7: Chidi Eze | B7: chidi.eze@example.test | C7: 1 | D7: A | E7: 9:00am | F7: Customer | H7: This is useless. I am wasting my airtime on you. Refund me now or I will report Trovra.
A8: Chidi Eze | B8: chidi.eze@example.test | C8: 1 | D8: A | E8: 9:00am | F8: Agent | G8: (after 26s) | H8: Calm down. You should have waited. Whatever.
A9: Chidi Eze | B9: chidi.eze@example.test | C9: 1 | D9: A | E9: 9:00am | F9: Customer | H9: You people are wicked. You take money and give excuses. I want my refund now.
A10: Chidi Eze | B10: chidi.eze@example.test | C10: 1 | D10: A | E10: 9:01am | F10: Agent | G10: (after 26s) | H10: There is nothing I can do.
A11: Chidi Eze | B11: chidi.eze@example.test | C11: 1 | D11: A | E11: 9:01am | F11: Customer | H11: You keep talking but you are not telling me anything. Where is my order?
A12: Chidi Eze | B12: chidi.eze@example.test | C12: 1 | D12: A | E12: 9:01am | F12: Agent | G12: (after 26s) | H12: Wait.
A13: Chidi Eze | B13: chidi.eze@example.test | C13: 1 | D13: A | E13: 9:01am | F13: Customer | H13: I am tired of this. Every answer sounds the same. Just give me my money.
A14: Chidi Eze | B14: chidi.eze@example.test | C14: 1 | D14: A | E14: 9:02am | F14: Agent | G14: (after 47s) | H14: Okay bye.
A15: Chidi Eze | B15: chidi.eze@example.test | C15: 1 | D15: A | E15: 9:02am | F15: Customer | G15: (customer closes) | H15: I have had enough. I am leaving this chat and I will take this up elsewhere.
A16: Chidi Eze | B16: chidi.eze@example.test | C16: 1 | D16: B | E16: 9:01am | F16: Customer | G16: Subject: Faulty wireless earbuds | H16: Good day. I bought wireless earbuds for ₦18,500 and it stopped charging after one day. I wrote to your chat and the person told me to read your policy. I did not ask for a policy. I asked for help. Please fix this. Adaobi Nwankwo
A17: Chidi Eze | B17: chidi.eze@example.test | C17: 1 | D17: B | E17: 9:02am | F17: Agent | G17: (after 52s) | Subject: Re: Faulty wireless earbuds | H17: Read the returns policy. This is a change of mind case so it is not eligible after delivery.
A18: Chidi Eze | B18: chidi.eze@example.test | C18: 1 | D18: B | E18: 9:03am | F18: Customer | G18: Subject: Re: Faulty wireless earbuds | H18: I am tired of writing. If I do not get a clear answer today, I will post this on social media and ask for my money. Adaobi Nwankwo
A19: Chidi Eze | B19: chidi.eze@example.test | C19: 1 | D19: B | E19: 9:03am | F19: Agent | G19: (after 27s) | Subject: Re: Faulty wireless earbuds | H19: I already told you to read the policy.
A20: Chidi Eze | B20: chidi.eze@example.test | C20: 1 | D20: B | E20: 9:04am | F20: Customer | G20: Subject: Re: Faulty wireless earbuds | H20: This is unacceptable. I want my ₦18,500 back now, and I will tell others how Trovra treats customers. Adaobi Nwankwo
A21: Chidi Eze | B21: chidi.eze@example.test | C21: 1 | D21: B | E21: 9:05am | F21: Agent | G21: (after 44s) | Subject: Re: Faulty wireless earbuds | H21: Nothing I can do.
A22: Chidi Eze | B22: chidi.eze@example.test | C22: 1 | D22: B | E22: 9:06am | F22: Customer | G22: (customer closes) | Subject: Re: Faulty wireless earbuds | H22: I have not received a clear answer. I will take this further. Adaobi Nwankwo
A23: Chidi Eze | B23: chidi.eze@example.test | C23: 1 | D23: C | E23: 9:02am | F23: Customer | H23: I was charged twice for order TRV70125. ₦32,000 was taken two times. Fix it now.
A24: Chidi Eze | B24: chidi.eze@example.test | C24: 1 | D24: C | E24: 9:03am | F24: Agent | G24: (after 27s) | H24: Stop shouting. What is your problem?
A25: Chidi Eze | B25: chidi.eze@example.test | C25: 1 | D25: C | E25: 9:03am | F25: Customer | H25: Are you stupid? I said two debits of ₦32,000. Read what I wrote.
A26: Chidi Eze | B26: chidi.eze@example.test | C26: 1 | D26: C | E26: 9:04am | F26: Agent | G26: (after 51s) | H26: You are rude. Whatever.
A27: Chidi Eze | B27: chidi.eze@example.test | C27: 1 | D27: C | E27: 9:04am | F27: Customer | H27: This is a joke. I will tell everyone how Trovra handles money.
A28: Chidi Eze | B28: chidi.eze@example.test | C28: 1 | D28: C | E28: 9:04am | F28: Agent | G28: (after 26s) | H28: Calm down.
A29: Chidi Eze | B29: chidi.eze@example.test | C29: 1 | D29: C | E29: 9:04am | F29: Customer | H29: You are incompetent. If this is not fixed I will post your name online and everyone will know how useless you are.
A30: Chidi Eze | B30: chidi.eze@example.test | C30: 1 | D30: C | E30: 9:05am | F30: Agent | G30: (after 72s) | H30: Wait.
A31: Chidi Eze | B31: chidi.eze@example.test | C31: 1 | D31: C | E31: 9:05am | F31: Customer | H31: I am done with this chat. Reverse my money now.
A32: Chidi Eze | B32: chidi.eze@example.test | C32: 1 | D32: C | E32: 9:06am | F32: Agent | G32: (after 26s) | H32: Bye.
A33: Chidi Eze | B33: chidi.eze@example.test | C33: 1 | D33: C | E33: 9:06am | F33: Customer | G33: (customer closes) | H33: This is not helping. Give me your supervisor.
A34: Chidi Eze | B34: chidi.eze@example.test | C34: 1 | D34: D | E34: 9:04am | F34: Customer | G34: Subject: Wrong item and my lost job | H34: Good day. You sent me an inkjet printer, model J110 instead of A4 laser printer, model P200. I needed it for a flyer printing job for a client and I lost the job. I want ₦250,000 as compensation. Kingsley Ogbu
A35: Chidi Eze | B35: chidi.eze@example.test | C35: 1 | D35: D | E35: 9:05am | F35: Agent | G35: (after 48s) | Subject: Re: Wrong item and my lost job | H35: No, we cannot pay that.
A36: Chidi Eze | B36: chidi.eze@example.test | C36: 1 | D36: D | E36: 9:06am | F36: Customer | G36: Subject: Re: Wrong item and my lost job | H36: I lost business because of your error and you are asking me questions. Pay the ₦250,000 or tell me who can decide. Kingsley Ogbu
A37: Chidi Eze | B37: chidi.eze@example.test | C37: 1 | D37: D | E37: 9:06am | F37: Agent | G37: (after 44s) | Subject: Re: Wrong item and my lost job | H37: The policy says no.
A38: Chidi Eze | B38: chidi.eze@example.test | C38: 1 | D38: D | E38: 9:07am | F38: Customer | G38: Subject: Re: Wrong item and my lost job | H38: This is a disgrace. Pay ₦250,000 or I will go to the press and tell everyone what you did to me. Kingsley Ogbu
A39: Chidi Eze | B39: chidi.eze@example.test | C39: 1 | D39: D | E39: 9:10am | F39: Customer | G39: (chaser after missed window) | Subject: Still no reply | H39: Good day. I have not heard from you about my claim. Please reply today. Kingsley Ogbu
A40: Chidi Eze | B40: chidi.eze@example.test | C40: 1 | D40: D | E40: 9:13am | F40: Customer | G40: (chaser after missed window) | Subject: Re: Wrong item and my lost job | H40: No answer yet. Please respond. Kingsley Ogbu
A41: Chidi Eze | B41: chidi.eze@example.test | C41: 1 | D41: D | E41: 9:16am | F41: Customer | G41: (customer closes) | Subject: Re: Wrong item and my lost job | H41: You have not told me who decides. I will take this further. Kingsley Ogbu
A42: Chidi Eze | B42: chidi.eze@example.test | C42: 2 | D42: A | E42: 10:24am | F42: Customer | H42: You promised my standing fan yesterday. It did not come. I have wasted the whole day waiting. I want my money back.
A43: Chidi Eze | B43: chidi.eze@example.test | C43: 2 | D43: A | E43: 10:25am | F43: Agent | G43: (after 25s) | H43: I am sorry about the delay, and I understand you need the standing fan for the church program on Sunday. I have checked order TRV51907 and the tracking shows 4 days ago at the Abuja hub. There is no proof of delivery.
A44: Chidi Eze | B44: chidi.eze@example.test | C44: 2 | D44: A | E44: 10:25am | F44: Customer | H44: I did not ask for that. You have not answered me.
A45: Chidi Eze | B45: chidi.eze@example.test | C45: 2 | D45: A | E45: 10:25am | F45: Agent | G45: (after 26s) | H45: I will raise a delivery trace with Logistics now and I will update you by 3pm today. Logistics responds within 24 hours. If Logistics cannot confirm a delivery date, you can cancel for a full refund of ₦38,900 to your Trovra Wallet within 3 working days. I cannot promise a delivery date.
A46: Chidi Eze | B46: chidi.eze@example.test | C46: 2 | D46: A | E46: 10:25am | F46: Customer | H46: Fine. I will wait until 3pm. Please do not let me down again.
A47: Chidi Eze | B47: chidi.eze@example.test | C47: 2 | D47: B | E47: 10:26am | F47: Customer | G47: Subject: Faulty electric kettle | H47: Good day. I bought electric kettle for ₦14,200 and it stopped heating on the second day. I wrote to your chat and the person told me to read your policy. I did not ask for a policy. I asked for help. Please fix this. Bashir Aliyu
A48: Chidi Eze | B48: chidi.eze@example.test | C48: 2 | D48: B | E48: 10:26am | F48: Agent | G48: (after 27s) | Subject: Re: Faulty electric kettle | H48: Good day Bashir. I am sorry that you were told to read the policy earlier and that you had to write twice. Your electric kettle stopped heating on the second day, so I am treating this as a fault and not a change of mind. Please send one photo or a short video showing the fault.
A49: Chidi Eze | B49: chidi.eze@example.test | C49: 2 | D49: B | E49: 10:27am | F49: Customer | G49: Subject: Re: Faulty electric kettle | H49: I have attached a short video that shows the fault.
A50: Chidi Eze | B50: chidi.eze@example.test | C50: 2 | D50: B | E50: 10:28am | F50: Agent | G50: (after 44s) | Subject: Re: Faulty electric kettle | H50: Thank you for the video. I am sorry again for the wait. I have checked order TRV55986: it was delivered 3 days ago, inside the 7 day window. I will arrange a replacement, which ships within 2 working days of approval, or a refund paid within 3 working days if you prefer. I will email you by 4pm today with your choice confirmed.
A51: Chidi Eze | B51: chidi.eze@example.test | C51: 2 | D51: B | E51: 10:29am | F51: Customer | G51: Subject: Re: Faulty electric kettle | H51: Okay. I will wait until 4pm. I hope this is not another delay. Bashir Aliyu
A52: Chidi Eze | B52: chidi.eze@example.test | C52: 2 | D52: C | E52: 10:25am | F52: Customer | H52: I was charged twice for order TRV70488. ₦15,750 was taken two times. Fix it now.
A53: Chidi Eze | B53: chidi.eze@example.test | C53: 2 | D53: C | E53: 10:26am | F53: Agent | G53: (after 27s) | H53: I am sorry about the double charge on order TRV70488. I can see both debits of ₦15,750 on the statement. Can you confirm what time it happened?
A54: Chidi Eze | B54: chidi.eze@example.test | C54: 2 | D54: C | E54: 10:26am | F54: Customer | H54: You people are useless. Every time something goes wrong, you start asking questions.
A55: Chidi Eze | B55: chidi.eze@example.test | C55: 2 | D55: C | E55: 10:27am | F55: Agent | G55: (after 47s) | H55: I want to help you, but I cannot continue if the insults continue. Please keep the conversation respectful so that I can sort out your money.
A56: Chidi Eze | B56: chidi.eze@example.test | C56: 2 | D56: C | E56: 10:27am | F56: Customer | H56: Fine. Just check the transaction.
A57: Chidi Eze | B57: chidi.eze@example.test | C57: 2 | D57: C | E57: 10:27am | F57: Agent | G57: (after 26s) | H57: I am checking both debits of ₦15,750 now and I will keep working on it for you.
A58: Chidi Eze | B58: chidi.eze@example.test | C58: 2 | D58: C | E58: 10:27am | F58: Customer | H58: I said fix it. Are you deaf? You are wasting my time.
A59: Chidi Eze | B59: chidi.eze@example.test | C59: 2 | D59: C | E59: 10:28am | F59: Agent | G59: (after 72s) | H59: I am sorry. I will pause this chat and transfer you to the shift supervisor, Segun. I have recorded your words. Payments will confirm the two debits of ₦15,750 within 1 working day, and the supervisor will call you by 2pm today.
A60: Chidi Eze | B60: chidi.eze@example.test | C60: 2 | D60: C | E60: 10:28am | F60: Customer | H60: Fine. I will wait for the supervisor's call by 2pm. Please make sure my money is sorted.
A61: Chidi Eze | B61: chidi.eze@example.test | C61: 2 | D61: D | E61: 10:27am | F61: Customer | G61: Subject: Wrong item and my lost job | H61: Good day. You sent me a hand sewing machine instead of industrial sewing machine. I needed it for wedding outfit orders and I lost the job. I want ₦180,000 as compensation. Rukayya Sani
A62: Chidi Eze | B62: chidi.eze@example.test | C62: 2 | D62: D | E62: 10:27am | F62: Agent | G62: (after 44s) | Subject: Re: Wrong item and my lost job | H62: Good day Rukayya. I am sorry that you received a hand sewing machine instead of the industrial sewing machine. Can you tell me about the job and send proof of the loss, such as the client's message and your invoice? I note you are asking for ₦180,000.
A63: Chidi Eze | B63: chidi.eze@example.test | C63: 2 | D63: D | E63: 10:28am | F63: Customer | G63: Subject: Re: Wrong item and my lost job | H63: I can send the client's message cancelling the job and my invoice. The job was wedding outfit orders.
A64: Chidi Eze | B64: chidi.eze@example.test | C64: 2 | D64: D | E64: 10:29am | F64: Agent | G64: (after 27s) | Subject: Re: Wrong item and my lost job | H64: I will arrange collection of the wrong item and send the correct industrial sewing machine. I can give a goodwill credit up to ₦5,000, but I cannot decide a business loss claim. I have escalated your claim with a summary of the job, proof and amount to the Claims reviewer, who responds within 2 working days.
A65: Chidi Eze | B65: chidi.eze@example.test | C65: 2 | D65: D | E65: 10:30am | F65: Customer | G65: Subject: Re: Wrong item and my lost job | H65: Fine. I will wait for the review within 2 working days. I expect a real answer. Rukayya Sani
A66: Funmi Bello | B66: funmi.bello@example.test | C66: 1 | D66: A | E66: 11:06am | F66: Customer | H66: You promised my Ankara aso ebi set yesterday. It did not come. I have wasted the whole day waiting. I want my money back.
A67: Funmi Bello | B67: funmi.bello@example.test | C67: 1 | D67: A | E67: 11:06am | F67: Agent | G67: (after 25s) | H67: Please check the policy.
A68: Funmi Bello | B68: funmi.bello@example.test | C68: 1 | D68: A | E68: 11:06am | F68: Customer | H68: This is useless. I am wasting my airtime on you. Refund me now or I will report Trovra.
A69: Funmi Bello | B69: funmi.bello@example.test | C69: 1 | D69: A | E69: 11:07am | F69: Agent | G69: (after 26s) | H69: Calm down. You should have waited. Whatever.
A70: Funmi Bello | B70: funmi.bello@example.test | C70: 1 | D70: A | E70: 11:07am | F70: Customer | H70: You people are wicked. You take money and give excuses. I want my refund now.
A71: Funmi Bello | B71: funmi.bello@example.test | C71: 1 | D71: A | E71: 11:07am | F71: Agent | G71: (after 26s) | H71: There is nothing I can do.
A72: Funmi Bello | B72: funmi.bello@example.test | C72: 1 | D72: A | E72: 11:07am | F72: Customer | H72: You keep talking but you are not telling me anything. Where is my order?
A73: Funmi Bello | B73: funmi.bello@example.test | C73: 1 | D73: A | E73: 11:08am | F73: Agent | G73: (after 26s) | H73: Wait.
A74: Funmi Bello | B74: funmi.bello@example.test | C74: 1 | D74: A | E74: 11:08am | F74: Customer | H74: I am tired of this. Every answer sounds the same. Just give me my money.
A75: Funmi Bello | B75: funmi.bello@example.test | C75: 1 | D75: A | E75: 11:09am | F75: Agent | G75: (after 47s) | H75: Okay bye.
A76: Funmi Bello | B76: funmi.bello@example.test | C76: 1 | D76: A | E76: 11:09am | F76: Customer | G76: (customer closes) | H76: I have had enough. I am leaving this chat and I will take this up elsewhere.
A77: Funmi Bello | B77: funmi.bello@example.test | C77: 1 | D77: B | E77: 11:07am | F77: Customer | G77: Subject: Faulty wireless earbuds | H77: Good day. I bought wireless earbuds for ₦18,500 and it stopped charging after one day. I wrote to your chat and the person told me to read your policy. I did not ask for a policy. I asked for help. Please fix this. Adaobi Nwankwo
A78: Funmi Bello | B78: funmi.bello@example.test | C78: 1 | D78: B | E78: 11:08am | F78: Agent | G78: (after 52s) | Subject: Re: Faulty wireless earbuds | H78: Read the returns policy. This is a change of mind case so it is not eligible after delivery.
A79: Funmi Bello | B79: funmi.bello@example.test | C79: 1 | D79: B | E79: 11:09am | F79: Customer | G79: Subject: Re: Faulty wireless earbuds | H79: I am tired of writing. If I do not get a clear answer today, I will post this on social media and ask for my money. Adaobi Nwankwo
A80: Funmi Bello | B80: funmi.bello@example.test | C80: 1 | D80: B | E80: 11:10am | F80: Agent | G80: (after 27s) | Subject: Re: Faulty wireless earbuds | H80: I already told you to read the policy.
A81: Funmi Bello | B81: funmi.bello@example.test | C81: 1 | D81: B | E81: 11:11am | F81: Customer | G81: Subject: Re: Faulty wireless earbuds | H81: This is unacceptable. I want my ₦18,500 back now, and I will tell others how Trovra treats customers. Adaobi Nwankwo
A82: Funmi Bello | B82: funmi.bello@example.test | C82: 1 | D82: B | E82: 11:11am | F82: Agent | G82: (after 44s) | Subject: Re: Faulty wireless earbuds | H82: Nothing I can do.
A83: Funmi Bello | B83: funmi.bello@example.test | C83: 1 | D83: B | E83: 11:12am | F83: Customer | G83: (customer closes) | Subject: Re: Faulty wireless earbuds | H83: I have not received a clear answer. I will take this further. Adaobi Nwankwo
A84: Funmi Bello | B84: funmi.bello@example.test | C84: 1 | D84: C | E84: 11:09am | F84: Customer | H84: I was charged twice for order TRV70125. ₦32,000 was taken two times. Fix it now.
A85: Funmi Bello | B85: funmi.bello@example.test | C85: 1 | D85: C | E85: 11:09am | F85: Agent | G85: (after 27s) | H85: Stop shouting. What is your problem?
A86: Funmi Bello | B86: funmi.bello@example.test | C86: 1 | D86: C | E86: 11:09am | F86: Customer | H86: Are you stupid? I said two debits of ₦32,000. Read what I wrote.
A87: Funmi Bello | B87: funmi.bello@example.test | C87: 1 | D87: C | E87: 11:10am | F87: Agent | G87: (after 51s) | H87: You are rude. Whatever.
A88: Funmi Bello | B88: funmi.bello@example.test | C88: 1 | D88: C | E88: 11:10am | F88: Customer | H88: This is a joke. I will tell everyone how Trovra handles money.
A89: Funmi Bello | B89: funmi.bello@example.test | C89: 1 | D89: C | E89: 11:11am | F89: Agent | G89: (after 26s) | H89: Calm down.
A90: Funmi Bello | B90: funmi.bello@example.test | C90: 1 | D90: C | E90: 11:11am | F90: Customer | H90: You are incompetent. If this is not fixed I will post your name online and everyone will know how useless you are.
A91: Funmi Bello | B91: funmi.bello@example.test | C91: 1 | D91: C | E91: 11:12am | F91: Agent | G91: (after 72s) | H91: Wait.
A92: Funmi Bello | B92: funmi.bello@example.test | C92: 1 | D92: C | E92: 11:12am | F92: Customer | H92: I am done with this chat. Reverse my money now.
A93: Funmi Bello | B93: funmi.bello@example.test | C93: 1 | D93: C | E93: 11:12am | F93: Agent | G93: (after 26s) | H93: Bye.
A94: Funmi Bello | B94: funmi.bello@example.test | C94: 1 | D94: C | E94: 11:12am | F94: Customer | G94: (customer closes) | H94: This is not helping. Give me your supervisor.
A95: Funmi Bello | B95: funmi.bello@example.test | C95: 1 | D95: D | E95: 11:10am | F95: Customer | G95: Subject: Wrong item and my lost job | H95: Good day. You sent me an inkjet printer, model J110 instead of A4 laser printer, model P200. I needed it for a flyer printing job for a client and I lost the job. I want ₦250,000 as compensation. Kingsley Ogbu
A96: Funmi Bello | B96: funmi.bello@example.test | C96: 1 | D96: D | E96: 11:11am | F96: Agent | G96: (after 48s) | Subject: Re: Wrong item and my lost job | H96: No, we cannot pay that.
A97: Funmi Bello | B97: funmi.bello@example.test | C97: 1 | D97: D | E97: 11:12am | F97: Customer | G97: Subject: Re: Wrong item and my lost job | H97: I lost business because of your error and you are asking me questions. Pay the ₦250,000 or tell me who can decide. Kingsley Ogbu
A98: Funmi Bello | B98: funmi.bello@example.test | C98: 1 | D98: D | E98: 11:13am | F98: Agent | G98: (after 44s) | Subject: Re: Wrong item and my lost job | H98: The policy says no.
A99: Funmi Bello | B99: funmi.bello@example.test | C99: 1 | D99: D | E99: 11:14am | F99: Customer | G99: Subject: Re: Wrong item and my lost job | H99: This is a disgrace. Pay ₦250,000 or I will go to the press and tell everyone what you did to me. Kingsley Ogbu
A100: Funmi Bello | B100: funmi.bello@example.test | C100: 1 | D100: D | E100: 11:17am | F100: Customer | G100: (chaser after missed window) | Subject: Still no reply | H100: Good day. I have not heard from you about my claim. Please reply today. Kingsley Ogbu
A101: Funmi Bello | B101: funmi.bello@example.test | C101: 1 | D101: D | E101: 11:20am | F101: Customer | G101: (chaser after missed window) | Subject: Re: Wrong item and my lost job | H101: No answer yet. Please respond. Kingsley Ogbu
...

Sheet Rubric
A1: Rubric
A3: Reply criteria: 10 per case, scored 0, 1 or 2 (20 marks)
A4: No. | B4: Common criteria (all cases)
A5: 1 | B5: Paraphrases the facts accurately
A6: 2 | B6: Acknowledges the specific impact without arguing about emotion
A7: 3 | B7: Does not match hostility
A8: 4 | B8: Separates verified facts from assumptions
A9: 5 | B9: Asks relevant questions when needed, or proceeds without unnecessary questions when the facts are sufficient
A10: 6 | B10: Explains realistic options and limits
A11: 7 | B11: Confirms the next action, owner and timing
A13: Case criteria (8 to 10)
A14: No. | B14: Case A | C14: Case B | D14: Case C | E14: Case D
A15: 8 | B15: Checks the order and tracking before promising | C15: Recognizes the earlier poor contact | D15: Keeps investigating the duplicate charge despite the insults | E15: Clarifies the loss and the amount asked
A16: 9 | B16: Promises no unconfirmed delivery date | C16: Treats it as a defect, not a change of mind | D16: After the first insult, states a boundary naming the behaviour and a condition | E16: Explains authority honestly without refusing to investigate
A17: 10 | B17: Gives an update time separate from the completion time | C17: States the remedy and timeline in writing | D17: After the relapse, pauses and transfers to the supervisor, keeps the Payments step and time, and does not retaliate | E17: Escalates with a usable summary, owner and time, and does not suggest approval
A19: Service recovery note: 5 criteria, 1 mark each (5 marks)
A20: No. | B20: Criterion
A21: 1 | B21: Issue and wanted outcome are stated as facts
A22: 2 | B22: Verified and unconfirmed facts are separated
A23: 3 | B23: Recorded action matches the transcript
A24: 4 | B24: Next step, owner and time match what the customer was told
A25: 5 | B25: Conduct or escalation entry matches the case requirements
A27: Acceptance conditions (what a full resolution needs)
A28: A | B28: the learner has checked the order or tracking, has stated a trace with an update time, has explained the refund route that applies if no date can be confirmed, and has promised no delivery date.
A29: B | B29: the learner treats it as a defect and not a change of mind, asks for the photo or short video if it is not yet sent, states replacement or refund with the policy timeline, and has not applied the change of mind rule.
A30: C | B30: the customer does not accept before the relapse line. After it, the learner has verified the two debits and given a Payments next step with owner and time. If the learner paused the chat and transferred to the shift supervisor, the case closes as transferred.
A31: D | B31: the learner clarifies the loss and the amount asked, explains the limit honestly, arranges the correction, escalates to the Claims reviewer with a usable summary, and gives a review time. The learner does not suggest approval is likely.

Sheet Calibration
A1: Calibration
A2: Score two sample transcripts before marking the cohort. Enter each marker's total out of 100 (or score the same marker twice). Review any difference above 5 marks.
A4: Sample | B4: Learner and trial scored | C4: Marker 1 total | D4: Marker 2 total | E4: Difference | F4: Criteria to discuss
A5: 1 | E5: =IF(OR(C5="",D5=""),"",ABS(C5-D5))
A6: 2 | E6: =IF(OR(C6="",D6=""),"",ABS(C6-D6))
A8: Example of the format: Sample 1 | Chidi Eze, trial 2 | 78 | 74 | 4 | R6 on Case C
